[
  {
    "name": "Naive-Basic",
    "read": [
      74,
      86,
      176,
      209,
      249,
      278,
      288,
      298,
      308,
      318,
      328,
      338,
      348,
      358,
      368,
      386,
      403,
      420,
      437,
      445,
      454,
      462,
      470,
      478,
      486,
      494,
      502,
      510,
      518,
      518
    ],
    "written": [
      4,
      5,
      6,
      7,
      8,
      9,
      10,
      11,
      12,
      16,
      17,
      18,
      19,
      20,
      21,
      24,
      27,
      30,
      33,
      34,
      37,
      38,
      39,
      40,
      41,
      42,
      43,
      44,
      45,
      46
    ],
    "pinned": [
      103,
      115,
      2205,
      2241,
      2661,
      2771,
      2781,
      2791,
      2801,
      2811,
      2821,
      2831,
      2841,
      2851,
      2861,
      2879,
      2897,
      2915,
      2933,
      2943,
      2953,
      2963,
      2973,
      2983,
      2993,
      3003,
      3013,
      3023,
      3033,
      3033
    ],
    "unpinned": [
      103,
      115,
      2205,
      2241,
      2661,
      2771,
      2781,
      2791,
      2801,
      2811,
      2821,
      2831,
      2841,
      2851,
      2861,
      2879,
      2897,
      2915,
      2933,
      2943,
      2953,
      2963,
      2973,
      2983,
      2993,
      3003,
      3013,
      3023,
      3033,
      3033
    ],
    "hit": [
      32,
      32,
      2032,
      2035,
      2415,
      2496,
      2496,
      2496,
      2496,
      2496,
      2496,
      2496,
      2496,
      2496,
      2496,
      2496,
      2497,
      2498,
      2499,
      2501,
      2503,
      2505,
      2507,
      2509,
      2511,
      2513,
      2515,
      2517,
      2519,
      2519
    ],
    "assigned": [
      71,
      83,
      173,
      206,
      246,
      275,
      285,
      295,
      305,
      315,
      325,
      335,
      345,
      355,
      365,
      383,
      400,
      417,
      434,
      442,
      450,
      458,
      466,
      474,
      482,
      490,
      498,
      506,
      514,
      514
    ],
    "ratio": [
      45.070000,
      38.554000,
      1174.566000,
      987.864000,
      981.707000,
      907.636000,
      875.789000,
      846.102000,
      818.361000,
      792.381000,
      768.000000,
      745.075000,
      723.478000,
      703.099000,
      683.836000,
      651.697000,
      624.250000,
      599.041000,
      575.806000,
      565.837000,
      556.222000,
      546.943000,
      537.983000,
      529.325000,
      520.954000,
      512.857000,
      505.020000,
      497.431000,
      490.078000,
      490.078000
    ],
    "elapsed": [
      0.001000,
      0.000000,
      0.083000,
      0.001000,
      0.017000,
      0.004000,
      0.000000,
      0.000000,
      0.000000,
      0.000000,
      0.000000,
      0.000000,
      0.000000,
      0.000000,
      0.000000,
      0.000000,
      0.000000,
      0.000000,
      0.000000,
      0.000000,
      0.000000,
      0.000000,
      0.000000,
      0.000000,
      0.000000,
      0.000000,
      0.000000,
      0.000000,
      0.000000,
      0.000000
    ]
  },
  {
    "name": "NaiveUp-Basic",
    "read": [
      74,
      86,
      176,
      209,
      249,
      278,
      288,
      298,
      308,
      318,
      328,
      338,
      348,
      358,
      368,
      386,
      403,
      420,
      437,
      445,
      454,
      462,
      470,
      478,
      486,
      494,
      502,
      510,
      518,
      518
    ],
    "written": [
      4,
      5,
      6,
      7,
      8,
      9,
      10,
      11,
      12,
      13,
      14,
      18,
      19,
      20,
      21,
      24,
      27,
      30,
      33,
      34,
      37,
      38,
      39,
      40,
      41,
      42,
      43,
      44,
      45,
      46
    ],
    "pinned": [
      103,
      115,
      2205,
      2241,
      2661,
      2771,
      2781,
      2791,
      2801,
      2811,
      2821,
      2831,
      2841,
      2851,
      2861,
      2879,
      2897,
      2915,
      2933,
      2943,
      2953,
      2963,
      2973,
      2983,
      2993,
      3003,
      3013,
      3023,
      3033,
      3033
    ],
    "unpinned": [
      103,
      115,
      2205,
      2241,
      2661,
      2771,
      2781,
      2791,
      2801,
      2811,
      2821,
      2831,
      2841,
      2851,
      2861,
      2879,
      2897,
      2915,
      2933,
      2943,
      2953,
      2963,
      2973,
      2983,
      2993,
      3003,
      3013,
      3023,
      3033,
      3033
    ],
    "hit": [
      32,
      32,
      2032,
      2035,
      2415,
      2496,
      2496,
      2496,
      2496,
      2496,
      2496,
      2496,
      2496,
      2496,
      2496,
      2496,
      2497,
      2498,
      2499,
      2501,
      2503,
      2505,
      2507,
      2509,
      2511,
      2513,
      2515,
      2517,
      2519,
      2519
    ],
    "assigned": [
      71,
      83,
      173,
      206,
      246,
      275,
      285,
      295,
      305,
      315,
      325,
      335,
      345,
      355,
      365,
      383,
      400,
      417,
      434,
      442,
      450,
      458,
      466,
      474,
      482,
      490,
      498,
      506,
      514,
      514
    ],
    "ratio": [
      45.070000,
      38.554000,
      1174.566000,
      987.864000,
      981.707000,
      907.636000,
      875.789000,
      846.102000,
      818.361000,
      792.381000,
      768.000000,
      745.075000,
      723.478000,
      703.099000,
      683.836000,
      651.697000,
      624.250000,
      599.041000,
      575.806000,
      565.837000,
      556.222000,
      546.943000,
      537.983000,
      529.325000,
      520.954000,
      512.857000,
      505.020000,
      497.431000,
      490.078000,
      490.078000
    ],
    "elapsed": [
      0.001000,
      0.000000,
      0.082000,
      0.001000,
      0.017000,
      0.004000,
      0.000000,
      0.000000,
      0.000000,
      0.000000,
      0.000000,
      0.000000,
      0.000000,
      0.000000,
      0.000000,
      0.000000,
      0.000000,
      0.000000,
      0.000000,
      0.000000,
      0.000000,
      0.000000,
      0.000000,
      0.000000,
      0.000000,
      0.000000,
      0.000000,
      0.000000,
      0.000000,
      0.000000
    ]
  },
  {
    "name": "NaiveBis-Basic",
    "read": [
      74,
      86,
      176,
      209,
      249,
      278,
      288,
      298,
      308,
      318,
      328,
      338,
      348,
      358,
      368,
      386,
      403,
      420,
      437,
      445,
      454,
      462,
      470,
      478,
      486,
      494,
      502,
      510,
      518,
      518
    ],
    "written": [
      4,
      5,
      6,
      7,
      8,
      9,
      10,
      11,
      12,
      13,
      14,
      15,
      16,
      17,
      18,
      24,
      27,
      30,
      33,
      34,
      37,
      38,
      39,
      40,
      41,
      42,
      43,
      44,
      45,
      46
    ],
    "pinned": [
      103,
      115,
      2205,
      2241,
      2661,
      2771,
      2781,
      2791,
      2801,
      2811,
      2821,
      2831,
      2841,
      2851,
      2861,
      2879,
      2897,
      2915,
      2933,
      2943,
      2953,
      2963,
      2973,
      2983,
      2993,
      3003,
      3013,
      3023,
      3033,
      3033
    ],
    "unpinned": [
      103,
      115,
      2205,
      2241,
      2661,
      2771,
      2781,
      2791,
      2801,
      2811,
      2821,
      2831,
      2841,
      2851,
      2861,
      2879,
      2897,
      2915,
      2933,
      2943,
      2953,
      2963,
      2973,
      2983,
      2993,
      3003,
      3013,
      3023,
      3033,
      3033
    ],
    "hit": [
      32,
      32,
      2032,
      2035,
      2415,
      2496,
      2496,
      2496,
      2496,
      2496,
      2496,
      2496,
      2496,
      2496,
      2496,
      2496,
      2497,
      2498,
      2499,
      2501,
      2503,
      2505,
      2507,
      2509,
      2511,
      2513,
      2515,
      2517,
      2519,
      2519
    ],
    "assigned": [
      71,
      83,
      173,
      206,
      246,
      275,
      285,
      295,
      305,
      315,
      325,
      335,
      345,
      355,
      365,
      383,
      400,
      417,
      434,
      442,
      450,
      458,
      466,
      474,
      482,
      490,
      498,
      506,
      514,
      514
    ],
    "ratio": [
      45.070000,
      38.554000,
      1174.566000,
      987.864000,
      981.707000,
      907.636000,
      875.789000,
      846.102000,
      818.361000,
      792.381000,
      768.000000,
      745.075000,
      723.478000,
      703.099000,
      683.836000,
      651.697000,
      624.250000,
      599.041000,
      575.806000,
      565.837000,
      556.222000,
      546.943000,
      537.983000,
      529.325000,
      520.954000,
      512.857000,
      505.020000,
      497.431000,
      490.078000,
      490.078000
    ],
    "elapsed": [
      0.002000,
      0.000000,
      0.082000,
      0.001000,
      0.017000,
      0.004000,
      0.000000,
      0.000000,
      0.000000,
      0.000000,
      0.000000,
      0.000000,
      0.000000,
      0.000000,
      0.000000,
      0.000000,
      0.000000,
      0.001000,
      0.000000,
      0.000000,
      0.000000,
      0.000000,
      0.000000,
      0.000000,
      0.000000,
      0.000000,
      0.000000,
      0.000000,
      0.000000,
      0.000000
    ]
  },
  {
    "name": "NaiveBisUp-Basic",
    "read": [
      74,
      86,
      176,
      209,
      249,
      278,
      288,
      298,
      308,
      318,
      328,
      338,
      348,
      358,
      368,
      386,
      403,
      420,
      437,
      445,
      454,
      462,
      470,
      478,
      486,
      494,
      502,
      510,
      518,
      518
    ],
    "written": [
      4,
      5,
      6,
      7,
      8,
      9,
      10,
      11,
      12,
      13,
      14,
      15,
      16,
      17,
      18,
      21,
      27,
      30,
      33,
      34,
      37,
      38,
      39,
      40,
      41,
      42,
      43,
      44,
      45,
      46
    ],
    "pinned": [
      103,
      115,
      2205,
      2241,
      2661,
      2771,
      2781,
      2791,
      2801,
      2811,
      2821,
      2831,
      2841,
      2851,
      2861,
      2879,
      2897,
      2915,
      2933,
      2943,
      2953,
      2963,
      2973,
      2983,
      2993,
      3003,
      3013,
      3023,
      3033,
      3033
    ],
    "unpinned": [
      103,
      115,
      2205,
      2241,
      2661,
      2771,
      2781,
      2791,
      2801,
      2811,
      2821,
      2831,
      2841,
      2851,
      2861,
      2879,
      2897,
      2915,
      2933,
      2943,
      2953,
      2963,
      2973,
      2983,
      2993,
      3003,
      3013,
      3023,
      3033,
      3033
    ],
    "hit": [
      32,
      32,
      2032,
      2035,
      2415,
      2496,
      2496,
      2496,
      2496,
      2496,
      2496,
      2496,
      2496,
      2496,
      2496,
      2496,
      2497,
      2498,
      2499,
      2501,
      2503,
      2505,
      2507,
      2509,
      2511,
      2513,
      2515,
      2517,
      2519,
      2519
    ],
    "assigned": [
      71,
      83,
      173,
      206,
      246,
      275,
      285,
      295,
      305,
      315,
      325,
      335,
      345,
      355,
      365,
      383,
      400,
      417,
      434,
      442,
      450,
      458,
      466,
      474,
      482,
      490,
      498,
      506,
      514,
      514
    ],
    "ratio": [
      45.070000,
      38.554000,
      1174.566000,
      987.864000,
      981.707000,
      907.636000,
      875.789000,
      846.102000,
      818.361000,
      792.381000,
      768.000000,
      745.075000,
      723.478000,
      703.099000,
      683.836000,
      651.697000,
      624.250000,
      599.041000,
      575.806000,
      565.837000,
      556.222000,
      546.943000,
      537.983000,
      529.325000,
      520.954000,
      512.857000,
      505.020000,
      497.431000,
      490.078000,
      490.078000
    ],
    "elapsed": [
      0.001000,
      0.000000,
      0.082000,
      0.001000,
      0.017000,
      0.004000,
      0.000000,
      0.000000,
      0.000000,
      0.000000,
      0.000000,
      0.000000,
      0.000000,
      0.000000,
      0.000000,
      0.000000,
      0.000000,
      0.000000,
      0.000000,
      0.000000,
      0.000000,
      0.000000,
      0.000000,
      0.000000,
      0.000000,
      0.000000,
      0.000000,
      0.000000,
      0.000000,
      0.000000
    ]
  },
  {
    "name": "FIFO-Basic",
    "read": [
      17,
      17,
      17,
      17,
      17,
      17,
      17,
      17,
      17,
      17,
      17,
      17,
      17,
      17,
      17,
      17,
      17,
      17,
      17,
      17,
      18,
      18,
      18,
      18,
      18,
      18,
      18,
      18,
      18,
      18
    ],
    "written": [
      4,
      5,
      6,
      7,
      8,
      9,
      10,
      11,
      12,
      13,
      14,
      15,
      16,
      17,
      18,
      21,
      24,
      30,
      33,
      34,
      37,
      38,
      39,
      40,
      41,
      42,
      43,
      44,
      45,
      46
    ],
    "pinned": [
      103,
      115,
      2205,
      2241,
      2661,
      2771,
      2781,
      2791,
      2801,
      2811,
      2821,
      2831,
      2841,
      2851,
      2861,
      2879,
      2897,
      2915,
      2933,
      2943,
      2953,
      2963,
      2973,
      2983,
      2993,
      3003,
      3013,
      3023,
      3033,
      3033
    ],
    "unpinned": [
      103,
      115,
      2205,
      2241,
      2661,
      2771,
      2781,
      2791,
      2801,
      2811,
      2821,
      2831,
      2841,
      2851,
      2861,
      2879,
      2897,
      2915,
      2933,
      2943,
      2953,
      2963,
      2973,
      2983,
      2993,
      3003,
      3013,
      3023,
      3033,
      3033
    ],
    "hit": [
      89,
      101,
      2191,
      2227,
      2647,
      2757,
      2767,
      2777,
      2787,
      2797,
      2807,
      2817,
      2827,
      2837,
      2847,
      2865,
      2883,
      2901,
      2919,
      2929,
      2939,
      2949,
      2959,
      2969,
      2979,
      2989,
      2999,
      3009,
      3019,
      3019
    ],
    "assigned": [
      14,
      14,
      14,
      14,
      14,
      14,
      14,
      14,
      14,
      14,
      14,
      14,
      14,
      14,
      14,
      14,
      14,
      14,
      14,
      14,
      14,
      14,
      14,
      14,
      14,
      14,
      14,
      14,
      14,
      14
    ],
    "ratio": [
      635.714000,
      721.429000,
      15650.000000,
      15907.143000,
      18907.143000,
      19692.857000,
      19764.285000,
      19835.715000,
      19907.143000,
      19978.572000,
      20050.000000,
      20121.428000,
      20192.857000,
      20264.285000,
      20335.715000,
      20464.285000,
      20592.857000,
      20721.428000,
      20850.000000,
      20921.428000,
      20992.857000,
      21064.285000,
      21135.715000,
      21207.143000,
      21278.572000,
      21350.000000,
      21421.428000,
      21492.857000,
      21564.285000,
      21564.285000
    ],
    "elapsed": [
      0.001000,
      0.000000,
      0.081000,
      0.001000,
      0.017000,
      0.004000,
      0.000000,
      0.000000,
      0.000000,
      0.000000,
      0.000000,
      0.000000,
      0.000000,
      0.000000,
      0.000000,
      0.000000,
      0.000000,
      0.000000,
      0.000000,
      0.000000,
      0.000000,
      0.000000,
      0.000000,
      0.000000,
      0.000000,
      0.000000,
      0.000000,
      0.000000,
      0.000000,
      0.000000
    ]
  },
  {
    "name": "FIFOTs-Basic",
    "read": [
      17,
      17,
      17,
      17,
      17,
      17,
      17,
      17,
      17,
      17,
      17,
      17,
      17,
      17,
      17,
      17,
      17,
      17,
      17,
      17,
      18,
      18,
      18,
      18,
      18,
      18,
      18,
      18,
      18,
      18
    ],
    "written": [
      4,
      5,
      6,
      7,
      8,
      9,
      10,
      11,
      12,
      13,
      14,
      15,
      16,
      17,
      18,
      21,
      24,
      27,
      33,
      34,
      37,
      38,
      39,
      40,
      41,
      42,
      43,
      44,
      45,
      46
    ],
    "pinned": [
      103,
      115,
      2205,
      2241,
      2661,
      2771,
      2781,
      2791,
      2801,
      2811,
      2821,
      2831,
      2841,
      2851,
      2861,
      2879,
      2897,
      2915,
      2933,
      2943,
      2953,
      2963,
      2973,
      2983,
      2993,
      3003,
      3013,
      3023,
      3033,
      3033
    ],
    "unpinned": [
      103,
      115,
      2205,
      2241,
      2661,
      2771,
      2781,
      2791,
      2801,
      2811,
      2821,
      2831,
      2841,
      2851,
      2861,
      2879,
      2897,
      2915,
      2933,
      2943,
      2953,
      2963,
      2973,
      2983,
      2993,
      3003,
      3013,
      3023,
      3033,
      3033
    ],
    "hit": [
      89,
      101,
      2191,
      2227,
      2647,
      2757,
      2767,
      2777,
      2787,
      2797,
      2807,
      2817,
      2827,
      2837,
      2847,
      2865,
      2883,
      2901,
      2919,
      2929,
      2939,
      2949,
      2959,
      2969,
      2979,
      2989,
      2999,
      3009,
      3019,
      3019
    ],
    "assigned": [
      14,
      14,
      14,
      14,
      14,
      14,
      14,
      14,
      14,
      14,
      14,
      14,
      14,
      14,
      14,
      14,
      14,
      14,
      14,
      14,
      14,
      14,
      14,
      14,
      14,
      14,
      14,
      14,
      14,
      14
    ],
    "ratio": [
      635.714000,
      721.429000,
      15650.000000,
      15907.143000,
      18907.143000,
      19692.857000,
      19764.285000,
      19835.715000,
      19907.143000,
      19978.572000,
      20050.000000,
      20121.428000,
      20192.857000,
      20264.285000,
      20335.715000,
      20464.285000,
      20592.857000,
      20721.428000,
      20850.000000,
      20921.428000,
      20992.857000,
      21064.285000,
      21135.715000,
      21207.143000,
      21278.572000,
      21350.000000,
      21421.428000,
      21492.857000,
      21564.285000,
      21564.285000
    ],
    "elapsed": [
      0.001000,
      0.000000,
      0.084000,
      0.001000,
      0.017000,
      0.004000,
      0.000000,
      0.000000,
      0.000000,
      0.000000,
      0.000000,
      0.000000,
      0.000000,
      0.000000,
      0.000000,
      0.000000,
      0.000000,
      0.000000,
      0.000000,
      0.000000,
      0.000000,
      0.000000,
      0.000000,
      0.000000,
      0.000000,
      0.000000,
      0.000000,
      0.000000,
      0.000000,
      0.000000
    ]
  },
  {
    "name": "FIFOUp-Basic",
    "read": [
      18,
      18,
      18,
      18,
      18,
      18,
      18,
      18,
      18,
      18,
      18,
      18,
      18,
      18,
      18,
      18,
      18,
      18,
      18,
      18,
      19,
      19,
      19,
      19,
      19,
      19,
      19,
      19,
      19,
      19
    ],
    "written": [
      4,
      5,
      6,
      7,
      8,
      9,
      10,
      11,
      12,
      13,
      14,
      15,
      16,
      17,
      18,
      21,
      24,
      27,
      30,
      31,
      37,
      38,
      39,
      40,
      41,
      42,
      43,
      44,
      45,
      46
    ],
    "pinned": [
      103,
      115,
      2205,
      2241,
      2661,
      2771,
      2781,
      2791,
      2801,
      2811,
      2821,
      2831,
      2841,
      2851,
      2861,
      2879,
      2897,
      2915,
      2933,
      2943,
      2953,
      2963,
      2973,
      2983,
      2993,
      3003,
      3013,
      3023,
      3033,
      3033
    ],
    "unpinned": [
      103,
      115,
      2205,
      2241,
      2661,
      2771,
      2781,
      2791,
      2801,
      2811,
      2821,
      2831,
      2841,
      2851,
      2861,
      2879,
      2897,
      2915,
      2933,
      2943,
      2953,
      2963,
      2973,
      2983,
      2993,
      3003,
      3013,
      3023,
      3033,
      3033
    ],
    "hit": [
      89,
      101,
      2191,
      2227,
      2647,
      2757,
      2767,
      2777,
      2787,
      2797,
      2807,
      2817,
      2827,
      2837,
      2847,
      2865,
      2883,
      2901,
      2919,
      2929,
      2939,
      2949,
      2959,
      2969,
      2979,
      2989,
      2999,
      3009,
      3019,
      3019
    ],
    "assigned": [
      14,
      14,
      14,
      14,
      14,
      14,
      14,
      14,
      14,
      14,
      14,
      14,
      14,
      14,
      14,
      14,
      14,
      14,
      14,
      14,
      14,
      14,
      14,
      14,
      14,
      14,
      14,
      14,
      14,
      14
    ],
    "ratio": [
      635.714000,
      721.429000,
      15650.000000,
      15907.143000,
      18907.143000,
      19692.857000,
      19764.285000,
      19835.715000,
      19907.143000,
      19978.572000,
      20050.000000,
      20121.428000,
      20192.857000,
      20264.285000,
      20335.715000,
      20464.285000,
      20592.857000,
      20721.428000,
      20850.000000,
      20921.428000,
      20992.857000,
      21064.285000,
      21135.715000,
      21207.143000,
      21278.572000,
      21350.000000,
      21421.428000,
      21492.857000,
      21564.285000,
      21564.285000
    ],
    "elapsed": [
      0.001000,
      0.000000,
      0.080000,
      0.001000,
      0.016000,
      0.004000,
      0.000000,
      0.000000,
      0.000000,
      0.000000,
      0.000000,
      0.000000,
      0.000000,
      0.000000,
      0.000000,
      0.000000,
      0.000000,
      0.000000,
      0.000000,
      0.000000,
      0.000000,
      0.000000,
      0.000000,
      0.000000,
      0.000000,
      0.000000,
      0.000000,
      0.000000,
      0.000000,
      0.000000
    ]
  },
  {
    "name": "LRU-Basic",
    "read": [
      18,
      18,
      18,
      18,
      18,
      18,
      18,
      18,
      18,
      18,
      18,
      18,
      18,
      18,
      18,
      18,
      18,
      18,
      18,
      18,
      19,
      19,
      19,
      19,
      19,
      19,
      19,
      19,
      19,
      19
    ],
    "written": [
      4,
      5,
      6,
      7,
      8,
      9,
      10,
      11,
      12,
      13,
      14,
      15,
      16,
      17,
      18,
      21,
      24,
      27,
      30,
      31,
      34,
      35,
      39,
      40,
      41,
      42,
      43,
      44,
      45,
      46
    ],
    "pinned": [
      103,
      115,
      2205,
      2241,
      2661,
      2771,
      2781,
      2791,
      2801,
      2811,
      2821,
      2831,
      2841,
      2851,
      2861,
      2879,
      2897,
      2915,
      2933,
      2943,
      2953,
      2963,
      2973,
      2983,
      2993,
      3003,
      3013,
      3023,
      3033,
      3033
    ],
    "unpinned": [
      103,
      115,
      2205,
      2241,
      2661,
      2771,
      2781,
      2791,
      2801,
      2811,
      2821,
      2831,
      2841,
      2851,
      2861,
      2879,
      2897,
      2915,
      2933,
      2943,
      2953,
      2963,
      2973,
      2983,
      2993,
      3003,
      3013,
      3023,
      3033,
      3033
    ],
    "hit": [
      89,
      101,
      2191,
      2227,
      2647,
      2757,
      2767,
      2777,
      2787,
      2797,
      2807,
      2817,
      2827,
      2837,
      2847,
      2865,
      2883,
      2901,
      2919,
      2929,
      2939,
      2949,
      2959,
      2969,
      2979,
      2989,
      2999,
      3009,
      3019,
      3019
    ],
    "assigned": [
      14,
      14,
      14,
      14,
      14,
      14,
      14,
      14,
      14,
      14,
      14,
      14,
      14,
      14,
      14,
      14,
      14,
      14,
      14,
      14,
      14,
      14,
      14,
      14,
      14,
      14,
      14,
      14,
      14,
      14
    ],
    "ratio": [
      635.714000,
      721.429000,
      15650.000000,
      15907.143000,
      18907.143000,
      19692.857000,
      19764.285000,
      19835.715000,
      19907.143000,
      19978.572000,
      20050.000000,
      20121.428000,
      20192.857000,
      20264.285000,
      20335.715000,
      20464.285000,
      20592.857000,
      20721.428000,
      20850.000000,
      20921.428000,
      20992.857000,
      21064.285000,
      21135.715000,
      21207.143000,
      21278.572000,
      21350.000000,
      21421.428000,
      21492.857000,
      21564.285000,
      21564.285000
    ],
    "elapsed": [
      0.002000,
      0.000000,
      0.083000,
      0.001000,
      0.017000,
      0.004000,
      0.000000,
      0.000000,
      0.000000,
      0.000000,
      0.000000,
      0.000000,
      0.000000,
      0.000000,
      0.000000,
      0.000000,
      0.000000,
      0.000000,
      0.000000,
      0.000000,
      0.000000,
      0.000000,
      0.000000,
      0.000000,
      0.000000,
      0.000000,
      0.000000,
      0.000000,
      0.000000,
      0.000000
    ]
  },
  {
    "name": "LRUTs-Basic",
    "read": [
      17,
      17,
      17,
      17,
      17,
      17,
      17,
      17,
      17,
      17,
      17,
      17,
      17,
      17,
      17,
      17,
      17,
      17,
      17,
      17,
      18,
      18,
      18,
      18,
      18,
      18,
      18,
      18,
      18,
      18
    ],
    "written": [
      7,
      8,
      9,
      10,
      11,
      12,
      13,
      14,
      15,
      16,
      17,
      18,
      19,
      20,
      21,
      24,
      27,
      30,
      33,
      34,
      37,
      38,
      39,
      40,
      41,
      45,
      46,
      47,
      48,
      49
    ],
    "pinned": [
      103,
      115,
      2205,
      2241,
      2661,
      2771,
      2781,
      2791,
      2801,
      2811,
      2821,
      2831,
      2841,
      2851,
      2861,
      2879,
      2897,
      2915,
      2933,
      2943,
      2953,
      2963,
      2973,
      2983,
      2993,
      3003,
      3013,
      3023,
      3033,
      3033
    ],
    "unpinned": [
      103,
      115,
      2205,
      2241,
      2661,
      2771,
      2781,
      2791,
      2801,
      2811,
      2821,
      2831,
      2841,
      2851,
      2861,
      2879,
      2897,
      2915,
      2933,
      2943,
      2953,
      2963,
      2973,
      2983,
      2993,
      3003,
      3013,
      3023,
      3033,
      3033
    ],
    "hit": [
      89,
      101,
      2191,
      2227,
      2647,
      2757,
      2767,
      2777,
      2787,
      2797,
      2807,
      2817,
      2827,
      2837,
      2847,
      2865,
      2883,
      2901,
      2919,
      2929,
      2939,
      2949,
      2959,
      2969,
      2979,
      2989,
      2999,
      3009,
      3019,
      3019
    ],
    "assigned": [
      14,
      14,
      14,
      14,
      14,
      14,
      14,
      14,
      14,
      14,
      14,
      14,
      14,
      14,
      14,
      14,
      14,
      14,
      14,
      14,
      14,
      14,
      14,
      14,
      14,
      14,
      14,
      14,
      14,
      14
    ],
    "ratio": [
      635.714000,
      721.429000,
      15650.000000,
      15907.143000,
      18907.143000,
      19692.857000,
      19764.285000,
      19835.715000,
      19907.143000,
      19978.572000,
      20050.000000,
      20121.428000,
      20192.857000,
      20264.285000,
      20335.715000,
      20464.285000,
      20592.857000,
      20721.428000,
      20850.000000,
      20921.428000,
      20992.857000,
      21064.285000,
      21135.715000,
      21207.143000,
      21278.572000,
      21350.000000,
      21421.428000,
      21492.857000,
      21564.285000,
      21564.285000
    ],
    "elapsed": [
      0.001000,
      0.000000,
      0.084000,
      0.001000,
      0.017000,
      0.004000,
      0.000000,
      0.000000,
      0.000000,
      0.000000,
      0.000000,
      0.000000,
      0.000000,
      0.000000,
      0.000000,
      0.000000,
      0.000000,
      0.000000,
      0.000000,
      0.000000,
      0.000000,
      0.000000,
      0.000000,
      0.000000,
      0.000000,
      0.000000,
      0.000000,
      0.000000,
      0.000000,
      0.000000
    ]
  },
  {
    "name": "LRUUp-Basic",
    "read": [
      17,
      17,
      17,
      17,
      17,
      17,
      17,
      17,
      17,
      17,
      17,
      17,
      17,
      17,
      17,
      17,
      17,
      17,
      17,
      17,
      18,
      18,
      18,
      18,
      18,
      18,
      18,
      18,
      18,
      18
    ],
    "written": [
      4,
      5,
      6,
      10,
      11,
      12,
      13,
      14,
      15,
      16,
      17,
      18,
      19,
      20,
      21,
      24,
      27,
      30,
      33,
      34,
      37,
      38,
      39,
      40,
      41,
      42,
      43,
      44,
      48,
      49
    ],
    "pinned": [
      103,
      115,
      2205,
      2241,
      2661,
      2771,
      2781,
      2791,
      2801,
      2811,
      2821,
      2831,
      2841,
      2851,
      2861,
      2879,
      2897,
      2915,
      2933,
      2943,
      2953,
      2963,
      2973,
      2983,
      2993,
      3003,
      3013,
      3023,
      3033,
      3033
    ],
    "unpinned": [
      103,
      115,
      2205,
      2241,
      2661,
      2771,
      2781,
      2791,
      2801,
      2811,
      2821,
      2831,
      2841,
      2851,
      2861,
      2879,
      2897,
      2915,
      2933,
      2943,
      2953,
      2963,
      2973,
      2983,
      2993,
      3003,
      3013,
      3023,
      3033,
      3033
    ],
    "hit": [
      89,
      101,
      2191,
      2227,
      2647,
      2757,
      2767,
      2777,
      2787,
      2797,
      2807,
      2817,
      2827,
      2837,
      2847,
      2865,
      2883,
      2901,
      2919,
      2929,
      2939,
      2949,
      2959,
      2969,
      2979,
      2989,
      2999,
      3009,
      3019,
      3019
    ],
    "assigned": [
      14,
      14,
      14,
      14,
      14,
      14,
      14,
      14,
      14,
      14,
      14,
      14,
      14,
      14,
      14,
      14,
      14,
      14,
      14,
      14,
      14,
      14,
      14,
      14,
      14,
      14,
      14,
      14,
      14,
      14
    ],
    "ratio": [
      635.714000,
      721.429000,
      15650.000000,
      15907.143000,
      18907.143000,
      19692.857000,
      19764.285000,
      19835.715000,
      19907.143000,
      19978.572000,
      20050.000000,
      20121.428000,
      20192.857000,
      20264.285000,
      20335.715000,
      20464.285000,
      20592.857000,
      20721.428000,
      20850.000000,
      20921.428000,
      20992.857000,
      21064.285000,
      21135.715000,
      21207.143000,
      21278.572000,
      21350.000000,
      21421.428000,
      21492.857000,
      21564.285000,
      21564.285000
    ],
    "elapsed": [
      0.001000,
      0.000000,
      0.088000,
      0.001000,
      0.019000,
      0.004000,
      0.000000,
      0.000000,
      0.000000,
      0.000000,
      0.000000,
      0.000000,
      0.000000,
      0.000000,
      0.000000,
      0.000000,
      0.001000,
      0.000000,
      0.000000,
      0.000000,
      0.000000,
      0.000000,
      0.000000,
      0.000000,
      0.000000,
      0.000000,
      0.000000,
      0.000000,
      0.000000,
      0.000000
    ]
  },
  {
    "name": "Clock-Basic",
    "read": [
      17,
      17,
      17,
      17,
      17,
      17,
      17,
      17,
      17,
      17,
      17,
      17,
      17,
      17,
      17,
      17,
      17,
      17,
      17,
      17,
      18,
      18,
      18,
      18,
      18,
      18,
      18,
      18,
      18,
      18
    ],
    "written": [
      4,
      5,
      6,
      7,
      8,
      12,
      13,
      14,
      15,
      16,
      17,
      18,
      19,
      20,
      21,
      24,
      27,
      30,
      33,
      34,
      37,
      38,
      39,
      40,
      41,
      42,
      43,
      44,
      45,
      46
    ],
    "pinned": [
      103,
      115,
      2205,
      2241,
      2661,
      2771,
      2781,
      2791,
      2801,
      2811,
      2821,
      2831,
      2841,
      2851,
      2861,
      2879,
      2897,
      2915,
      2933,
      2943,
      2953,
      2963,
      2973,
      2983,
      2993,
      3003,
      3013,
      3023,
      3033,
      3033
    ],
    "unpinned": [
      103,
      115,
      2205,
      2241,
      2661,
      2771,
      2781,
      2791,
      2801,
      2811,
      2821,
      2831,
      2841,
      2851,
      2861,
      2879,
      2897,
      2915,
      2933,
      2943,
      2953,
      2963,
      2973,
      2983,
      2993,
      3003,
      3013,
      3023,
      3033,
      3033
    ],
    "hit": [
      89,
      101,
      2191,
      2227,
      2647,
      2757,
      2767,
      2777,
      2787,
      2797,
      2807,
      2817,
      2827,
      2837,
      2847,
      2865,
      2883,
      2901,
      2919,
      2929,
      2939,
      2949,
      2959,
      2969,
      2979,
      2989,
      2999,
      3009,
      3019,
      3019
    ],
    "assigned": [
      14,
      14,
      14,
      14,
      14,
      14,
      14,
      14,
      14,
      14,
      14,
      14,
      14,
      14,
      14,
      14,
      14,
      14,
      14,
      14,
      14,
      14,
      14,
      14,
      14,
      14,
      14,
      14,
      14,
      14
    ],
    "ratio": [
      635.714000,
      721.429000,
      15650.000000,
      15907.143000,
      18907.143000,
      19692.857000,
      19764.285000,
      19835.715000,
      19907.143000,
      19978.572000,
      20050.000000,
      20121.428000,
      20192.857000,
      20264.285000,
      20335.715000,
      20464.285000,
      20592.857000,
      20721.428000,
      20850.000000,
      20921.428000,
      20992.857000,
      21064.285000,
      21135.715000,
      21207.143000,
      21278.572000,
      21350.000000,
      21421.428000,
      21492.857000,
      21564.285000,
      21564.285000
    ],
    "elapsed": [
      0.001000,
      0.000000,
      0.082000,
      0.001000,
      0.017000,
      0.004000,
      0.000000,
      0.000000,
      0.000000,
      0.000000,
      0.000000,
      0.000000,
      0.000000,
      0.000000,
      0.000000,
      0.000000,
      0.000000,
      0.000000,
      0.000000,
      0.000000,
      0.000000,
      0.000000,
      0.000000,
      0.000000,
      0.000000,
      0.000000,
      0.000000,
      0.000000,
      0.000000,
      0.000000
    ]
  },
  {
    "name": "ClockUp-Basic",
    "read": [
      17,
      17,
      17,
      17,
      17,
      17,
      17,
      17,
      17,
      17,
      17,
      17,
      17,
      17,
      17,
      17,
      17,
      17,
      17,
      17,
      18,
      18,
      18,
      18,
      18,
      18,
      18,
      18,
      18,
      18
    ],
    "written": [
      4,
      5,
      6,
      7,
      8,
      9,
      10,
      11,
      12,
      16,
      17,
      18,
      19,
      20,
      21,
      24,
      27,
      30,
      33,
      34,
      37,
      38,
      39,
      40,
      41,
      42,
      43,
      44,
      45,
      46
    ],
    "pinned": [
      103,
      115,
      2205,
      2241,
      2661,
      2771,
      2781,
      2791,
      2801,
      2811,
      2821,
      2831,
      2841,
      2851,
      2861,
      2879,
      2897,
      2915,
      2933,
      2943,
      2953,
      2963,
      2973,
      2983,
      2993,
      3003,
      3013,
      3023,
      3033,
      3033
    ],
    "unpinned": [
      103,
      115,
      2205,
      2241,
      2661,
      2771,
      2781,
      2791,
      2801,
      2811,
      2821,
      2831,
      2841,
      2851,
      2861,
      2879,
      2897,
      2915,
      2933,
      2943,
      2953,
      2963,
      2973,
      2983,
      2993,
      3003,
      3013,
      3023,
      3033,
      3033
    ],
    "hit": [
      89,
      101,
      2191,
      2227,
      2647,
      2757,
      2767,
      2777,
      2787,
      2797,
      2807,
      2817,
      2827,
      2837,
      2847,
      2865,
      2883,
      2901,
      2919,
      2929,
      2939,
      2949,
      2959,
      2969,
      2979,
      2989,
      2999,
      3009,
      3019,
      3019
    ],
    "assigned": [
      14,
      14,
      14,
      14,
      14,
      14,
      14,
      14,
      14,
      14,
      14,
      14,
      14,
      14,
      14,
      14,
      14,
      14,
      14,
      14,
      14,
      14,
      14,
      14,
      14,
      14,
      14,
      14,
      14,
      14
    ],
    "ratio": [
      635.714000,
      721.429000,
      15650.000000,
      15907.143000,
      18907.143000,
      19692.857000,
      19764.285000,
      19835.715000,
      19907.143000,
      19978.572000,
      20050.000000,
      20121.428000,
      20192.857000,
      20264.285000,
      20335.715000,
      20464.285000,
      20592.857000,
      20721.428000,
      20850.000000,
      20921.428000,
      20992.857000,
      21064.285000,
      21135.715000,
      21207.143000,
      21278.572000,
      21350.000000,
      21421.428000,
      21492.857000,
      21564.285000,
      21564.285000
    ],
    "elapsed": [
      0.001000,
      0.000000,
      0.081000,
      0.001000,
      0.017000,
      0.004000,
      0.000000,
      0.000000,
      0.000000,
      0.000000,
      0.000000,
      0.000000,
      0.000000,
      0.000000,
      0.000000,
      0.000000,
      0.000000,
      0.000000,
      0.000000,
      0.000000,
      0.000000,
      0.000000,
      0.000000,
      0.000000,
      0.000000,
      0.000000,
      0.000000,
      0.000000,
      0.000000,
      0.000000
    ]
  },
  {
    "name": "Naive-Heuristic",
    "read": [
      179,
      192,
      268,
      341,
      401,
      450,
      473,
      494,
      515,
      536,
      557,
      578,
      599,
      620,
      641,
      658,
      675,
      692,
      709,
      730,
      752,
      773,
      794,
      815,
      836,
      857,
      878,
      899,
      920,
      920
    ],
    "written": [
      4,
      5,
      262,
      270,
      296,
      332,
      333,
      334,
      335,
      336,
      337,
      338,
      339,
      340,
      341,
      344,
      347,
      353,
      356,
      357,
      360,
      361,
      362,
      363,
      364,
      365,
      366,
      367,
      368,
      369
    ],
    "pinned": [
      118,
      131,
      216,
      304,
      379,
      456,
      479,
      502,
      525,
      548,
      571,
      594,
      617,
      640,
      663,
      681,
      699,
      717,
      735,
      758,
      781,
      804,
      827,
      850,
      873,
      896,
      919,
      942,
      965,
      965
    ],
    "unpinned": [
      118,
      131,
      216,
      304,
      379,
      456,
      479,
      502,
      525,
      548,
      571,
      594,
      617,
      640,
      663,
      681,
      699,
      717,
      735,
      758,
      781,
      804,
      827,
      850,
      873,
      896,
      919,
      942,
      965,
      965
    ],
    "hit": [
      29,
      29,
      38,
      53,
      68,
      96,
      96,
      98,
      100,
      102,
      104,
      106,
      108,
      110,
      112,
      113,
      114,
      115,
      116,
      118,
      120,
      122,
      124,
      126,
      128,
      130,
      132,
      134,
      136,
      136
    ],
    "assigned": [
      89,
      102,
      178,
      251,
      311,
      360,
      383,
      404,
      425,
      446,
      467,
      488,
      509,
      530,
      551,
      568,
      585,
      602,
      619,
      640,
      661,
      682,
      703,
      724,
      745,
      766,
      787,
      808,
      829,
      829
    ],
    "ratio": [
      32.584000,
      28.431000,
      21.348000,
      21.116000,
      21.865000,
      26.667000,
      25.065000,
      24.257000,
      23.529000,
      22.870000,
      22.270000,
      21.721000,
      21.218000,
      20.755000,
      20.327000,
      19.894000,
      19.487000,
      19.103000,
      18.740000,
      18.438000,
      18.154000,
      17.889000,
      17.639000,
      17.403000,
      17.181000,
      16.971000,
      16.773000,
      16.584000,
      16.405000,
      16.405000
    ],
    "elapsed": [
      0.002000,
      0.000000,
      0.022000,
      0.003000,
      0.003000,
      0.004000,
      0.000000,
      0.000000,
      0.000000,
      0.000000,
      0.001000,
      0.001000,
      0.000000,
      0.000000,
      0.000000,
      0.000000,
      0.000000,
      0.000000,
      0.000000,
      0.001000,
      0.000000,
      0.001000,
      0.000000,
      0.000000,
      0.000000,
      0.000000,
      0.000000,
      0.000000,
      0.000000,
      0.000000
    ]
  },
  {
    "name": "NaiveUp-Heuristic",
    "read": [
      179,
      192,
      259,
      331,
      390,
      437,
      459,
      479,
      499,
      519,
      539,
      559,
      579,
      599,
      619,
      635,
      651,
      667,
      683,
      703,
      724,
      744,
      764,
      784,
      804,
      824,
      844,
      864,
      884,
      884
    ],
    "written": [
      4,
      5,
      256,
      261,
      284,
      322,
      323,
      324,
      325,
      326,
      327,
      328,
      329,
      330,
      331,
      334,
      337,
      340,
      343,
      344,
      347,
      348,
      349,
      350,
      351,
      352,
      353,
      354,
      355,
      359
    ],
    "pinned": [
      118,
      131,
      216,
      304,
      379,
      456,
      479,
      502,
      525,
      548,
      571,
      594,
      617,
      640,
      663,
      681,
      699,
      717,
      735,
      758,
      781,
      804,
      827,
      850,
      873,
      896,
      919,
      942,
      965,
      965
    ],
    "unpinned": [
      118,
      131,
      216,
      304,
      379,
      456,
      479,
      502,
      525,
      548,
      571,
      594,
      617,
      640,
      663,
      681,
      699,
      717,
      735,
      758,
      781,
      804,
      827,
      850,
      873,
      896,
      919,
      942,
      965,
      965
    ],
    "hit": [
      29,
      29,
      47,
      63,
      79,
      109,
      110,
      113,
      116,
      119,
      122,
      125,
      128,
      131,
      134,
      136,
      138,
      140,
      142,
      145,
      148,
      151,
      154,
      157,
      160,
      163,
      166,
      169,
      172,
      172
    ],
    "assigned": [
      89,
      102,
      169,
      241,
      300,
      347,
      369,
      389,
      409,
      429,
      449,
      469,
      489,
      509,
      529,
      545,
      561,
      577,
      593,
      613,
      633,
      653,
      673,
      693,
      713,
      733,
      753,
      773,
      793,
      793
    ],
    "ratio": [
      32.584000,
      28.431000,
      27.811000,
      26.141000,
      26.333000,
      31.412000,
      29.810000,
      29.049000,
      28.362000,
      27.739000,
      27.171000,
      26.652000,
      26.176000,
      25.737000,
      25.331000,
      24.954000,
      24.599000,
      24.263000,
      23.946000,
      23.654000,
      23.381000,
      23.124000,
      22.883000,
      22.655000,
      22.440000,
      22.237000,
      22.045000,
      21.863000,
      21.690000,
      21.690000
    ],
    "elapsed": [
      0.002000,
      0.000000,
      0.022000,
      0.003000,
      0.003000,
      0.004000,
      0.000000,
      0.000000,
      0.000000,
      0.000000,
      0.000000,
      0.000000,
      0.000000,
      0.000000,
      0.000000,
      0.000000,
      0.000000,
      0.000000,
      0.000000,
      0.001000,
      0.000000,
      0.000000,
      0.000000,
      0.000000,
      0.001000,
      0.000000,
      0.000000,
      0.000000,
      0.000000,
      0.000000
    ]
  },
  {
    "name": "NaiveBis-Heuristic",
    "read": [
      179,
      192,
      268,
      341,
      401,
      450,
      473,
      494,
      515,
      536,
      557,
      578,
      599,
      620,
      641,
      658,
      675,
      692,
      709,
      730,
      752,
      773,
      794,
      815,
      836,
      857,
      878,
      899,
      920,
      920
    ],
    "written": [
      4,
      5,
      265,
      270,
      296,
      332,
      333,
      334,
      335,
      336,
      337,
      338,
      339,
      340,
      341,
      344,
      350,
      353,
      356,
      357,
      360,
      361,
      362,
      363,
      364,
      365,
      366,
      367,
      368,
      369
    ],
    "pinned": [
      118,
      131,
      216,
      304,
      379,
      456,
      479,
      502,
      525,
      548,
      571,
      594,
      617,
      640,
      663,
      681,
      699,
      717,
      735,
      758,
      781,
      804,
      827,
      850,
      873,
      896,
      919,
      942,
      965,
      965
    ],
    "unpinned": [
      118,
      131,
      216,
      304,
      379,
      456,
      479,
      502,
      525,
      548,
      571,
      594,
      617,
      640,
      663,
      681,
      699,
      717,
      735,
      758,
      781,
      804,
      827,
      850,
      873,
      896,
      919,
      942,
      965,
      965
    ],
    "hit": [
      29,
      29,
      38,
      53,
      68,
      96,
      96,
      98,
      100,
      102,
      104,
      106,
      108,
      110,
      112,
      113,
      114,
      115,
      116,
      118,
      120,
      122,
      124,
      126,
      128,
      130,
      132,
      134,
      136,
      136
    ],
    "assigned": [
      89,
      102,
      178,
      251,
      311,
      360,
      383,
      404,
      425,
      446,
      467,
      488,
      509,
      530,
      551,
      568,
      585,
      602,
      619,
      640,
      661,
      682,
      703,
      724,
      745,
      766,
      787,
      808,
      829,
      829
    ],
    "ratio": [
      32.584000,
      28.431000,
      21.348000,
      21.116000,
      21.865000,
      26.667000,
      25.065000,
      24.257000,
      23.529000,
      22.870000,
      22.270000,
      21.721000,
      21.218000,
      20.755000,
      20.327000,
      19.894000,
      19.487000,
      19.103000,
      18.740000,
      18.438000,
      18.154000,
      17.889000,
      17.639000,
      17.403000,
      17.181000,
      16.971000,
      16.773000,
      16.584000,
      16.405000,
      16.405000
    ],
    "elapsed": [
      0.001000,
      0.000000,
      0.022000,
      0.003000,
      0.003000,
      0.004000,
      0.000000,
      0.000000,
      0.000000,
      0.000000,
      0.000000,
      0.000000,
      0.000000,
      0.000000,
      0.000000,
      0.000000,
      0.000000,
      0.000000,
      0.000000,
      0.001000,
      0.000000,
      0.000000,
      0.000000,
      0.000000,
      0.000000,
      0.000000,
      0.000000,
      0.000000,
      0.000000,
      0.000000
    ]
  },
  {
    "name": "NaiveBisUp-Heuristic",
    "read": [
      180,
      193,
      260,
      332,
      391,
      438,
      460,
      480,
      500,
      520,
      540,
      560,
      580,
      600,
      620,
      636,
      652,
      668,
      684,
      704,
      725,
      745,
      765,
      785,
      805,
      825,
      845,
      865,
      885,
      885
    ],
    "written": [
      4,
      5,
      253,
      258,
      281,
      319,
      320,
      321,
      322,
      323,
      324,
      325,
      326,
      327,
      328,
      331,
      334,
      337,
      340,
      341,
      344,
      345,
      346,
      347,
      351,
      352,
      353,
      354,
      355,
      356
    ],
    "pinned": [
      118,
      131,
      216,
      304,
      379,
      456,
      479,
      502,
      525,
      548,
      571,
      594,
      617,
      640,
      663,
      681,
      699,
      717,
      735,
      758,
      781,
      804,
      827,
      850,
      873,
      896,
      919,
      942,
      965,
      965
    ],
    "unpinned": [
      118,
      131,
      216,
      304,
      379,
      456,
      479,
      502,
      525,
      548,
      571,
      594,
      617,
      640,
      663,
      681,
      699,
      717,
      735,
      758,
      781,
      804,
      827,
      850,
      873,
      896,
      919,
      942,
      965,
      965
    ],
    "hit": [
      29,
      29,
      47,
      63,
      79,
      109,
      110,
      113,
      116,
      119,
      122,
      125,
      128,
      131,
      134,
      136,
      138,
      140,
      142,
      145,
      148,
      151,
      154,
      157,
      160,
      163,
      166,
      169,
      172,
      172
    ],
    "assigned": [
      89,
      102,
      169,
      241,
      300,
      347,
      369,
      389,
      409,
      429,
      449,
      469,
      489,
      509,
      529,
      545,
      561,
      577,
      593,
      613,
      633,
      653,
      673,
      693,
      713,
      733,
      753,
      773,
      793,
      793
    ],
    "ratio": [
      32.584000,
      28.431000,
      27.811000,
      26.141000,
      26.333000,
      31.412000,
      29.810000,
      29.049000,
      28.362000,
      27.739000,
      27.171000,
      26.652000,
      26.176000,
      25.737000,
      25.331000,
      24.954000,
      24.599000,
      24.263000,
      23.946000,
      23.654000,
      23.381000,
      23.124000,
      22.883000,
      22.655000,
      22.440000,
      22.237000,
      22.045000,
      21.863000,
      21.690000,
      21.690000
    ],
    "elapsed": [
      0.001000,
      0.000000,
      0.021000,
      0.002000,
      0.003000,
      0.004000,
      0.000000,
      0.000000,
      0.000000,
      0.000000,
      0.000000,
      0.000000,
      0.000000,
      0.000000,
      0.000000,
      0.000000,
      0.000000,
      0.000000,
      0.000000,
      0.001000,
      0.000000,
      0.000000,
      0.000000,
      0.000000,
      0.000000,
      0.000000,
      0.000000,
      0.000000,
      0.000000,
      0.000000
    ]
  },
  {
    "name": "FIFO-Heuristic",
    "read": [
      106,
      106,
      118,
      125,
      131,
      136,
      136,
      136,
      136,
      136,
      136,
      136,
      136,
      136,
      136,
      136,
      136,
      136,
      136,
      136,
      137,
      137,
      137,
      137,
      137,
      137,
      137,
      137,
      137,
      137
    ],
    "written": [
      4,
      5,
      256,
      261,
      284,
      320,
      321,
      322,
      323,
      324,
      325,
      326,
      327,
      328,
      332,
      335,
      338,
      341,
      344,
      345,
      348,
      349,
      350,
      351,
      352,
      353,
      354,
      355,
      356,
      357
    ],
    "pinned": [
      118,
      131,
      216,
      304,
      379,
      456,
      479,
      502,
      525,
      548,
      571,
      594,
      617,
      640,
      663,
      681,
      699,
      717,
      735,
      758,
      781,
      804,
      827,
      850,
      873,
      896,
      919,
      942,
      965,
      965
    ],
    "unpinned": [
      118,
      131,
      216,
      304,
      379,
      456,
      479,
      502,
      525,
      548,
      571,
      594,
      617,
      640,
      663,
      681,
      699,
      717,
      735,
      758,
      781,
      804,
      827,
      850,
      873,
      896,
      919,
      942,
      965,
      965
    ],
    "hit": [
      102,
      115,
      188,
      269,
      338,
      410,
      433,
      456,
      479,
      502,
      525,
      548,
      571,
      594,
      617,
      635,
      653,
      671,
      689,
      712,
      735,
      758,
      781,
      804,
      827,
      850,
      873,
      896,
      919,
      919
    ],
    "assigned": [
      16,
      16,
      28,
      35,
      41,
      46,
      46,
      46,
      46,
      46,
      46,
      46,
      46,
      46,
      46,
      46,
      46,
      46,
      46,
      46,
      46,
      46,
      46,
      46,
      46,
      46,
      46,
      46,
      46,
      46
    ],
    "ratio": [
      637.500000,
      718.750000,
      671.429000,
      768.571000,
      824.390000,
      891.304000,
      941.304000,
      991.304000,
      1041.304000,
      1091.304000,
      1141.304000,
      1191.304000,
      1241.304000,
      1291.304000,
      1341.304000,
      1380.435000,
      1419.565000,
      1458.696000,
      1497.826000,
      1547.826000,
      1597.826000,
      1647.826000,
      1697.826000,
      1747.826000,
      1797.826000,
      1847.826000,
      1897.826000,
      1947.826000,
      1997.826000,
      1997.826000
    ],
    "elapsed": [
      0.001000,
      0.000000,
      0.021000,
      0.002000,
      0.003000,
      0.003000,
      0.000000,
      0.000000,
      0.000000,
      0.000000,
      0.000000,
      0.000000,
      0.000000,
      0.000000,
      0.000000,
      0.000000,
      0.000000,
      0.000000,
      0.000000,
      0.000000,
      0.000000,
      0.000000,
      0.000000,
      0.000000,
      0.000000,
      0.000000,
      0.000000,
      0.000000,
      0.000000,
      0.000000
    ]
  },
  {
    "name": "FIFOTs-Heuristic",
    "read": [
      106,
      106,
      118,
      125,
      131,
      136,
      136,
      136,
      136,
      136,
      136,
      136,
      136,
      136,
      136,
      136,
      136,
      136,
      136,
      136,
      137,
      137,
      137,
      137,
      137,
      137,
      137,
      137,
      137,
      137
    ],
    "written": [
      4,
      5,
      253,
      258,
      281,
      319,
      320,
      321,
      322,
      323,
      324,
      325,
      326,
      327,
      328,
      331,
      334,
      337,
      340,
      341,
      344,
      348,
      349,
      350,
      351,
      352,
      353,
      354,
      355,
      356
    ],
    "pinned": [
      118,
      131,
      216,
      304,
      379,
      456,
      479,
      502,
      525,
      548,
      571,
      594,
      617,
      640,
      663,
      681,
      699,
      717,
      735,
      758,
      781,
      804,
      827,
      850,
      873,
      896,
      919,
      942,
      965,
      965
    ],
    "unpinned": [
      118,
      131,
      216,
      304,
      379,
      456,
      479,
      502,
      525,
      548,
      571,
      594,
      617,
      640,
      663,
      681,
      699,
      717,
      735,
      758,
      781,
      804,
      827,
      850,
      873,
      896,
      919,
      942,
      965,
      965
    ],
    "hit": [
      102,
      115,
      188,
      269,
      338,
      410,
      433,
      456,
      479,
      502,
      525,
      548,
      571,
      594,
      617,
      635,
      653,
      671,
      689,
      712,
      735,
      758,
      781,
      804,
      827,
      850,
      873,
      896,
      919,
      919
    ],
    "assigned": [
      16,
      16,
      28,
      35,
      41,
      46,
      46,
      46,
      46,
      46,
      46,
      46,
      46,
      46,
      46,
      46,
      46,
      46,
      46,
      46,
      46,
      46,
      46,
      46,
      46,
      46,
      46,
      46,
      46,
      46
    ],
    "ratio": [
      637.500000,
      718.750000,
      671.429000,
      768.571000,
      824.390000,
      891.304000,
      941.304000,
      991.304000,
      1041.304000,
      1091.304000,
      1141.304000,
      1191.304000,
      1241.304000,
      1291.304000,
      1341.304000,
      1380.435000,
      1419.565000,
      1458.696000,
      1497.826000,
      1547.826000,
      1597.826000,
      1647.826000,
      1697.826000,
      1747.826000,
      1797.826000,
      1847.826000,
      1897.826000,
      1947.826000,
      1997.826000,
      1997.826000
    ],
    "elapsed": [
      0.001000,
      0.000000,
      0.021000,
      0.002000,
      0.003000,
      0.004000,
      0.000000,
      0.000000,
      0.000000,
      0.000000,
      0.000000,
      0.000000,
      0.000000,
      0.000000,
      0.000000,
      0.000000,
      0.000000,
      0.000000,
      0.000000,
      0.001000,
      0.000000,
      0.000000,
      0.000000,
      0.000000,
      0.000000,
      0.000000,
      0.000000,
      0.000000,
      0.000000,
      0.000000
    ]
  },
  {
    "name": "FIFOUp-Heuristic",
    "read": [
      106,
      106,
      118,
      125,
      131,
      136,
      136,
      136,
      136,
      136,
      136,
      136,
      136,
      136,
      136,
      136,
      136,
      136,
      136,
      136,
      137,
      137,
      137,
      137,
      137,
      137,
      137,
      137,
      137,
      137
    ],
    "written": [
      4,
      5,
      256,
      261,
      284,
      320,
      321,
      322,
      323,
      324,
      325,
      329,
      330,
      331,
      332,
      335,
      338,
      341,
      344,
      345,
      348,
      349,
      350,
      351,
      352,
      353,
      354,
      355,
      356,
      357
    ],
    "pinned": [
      118,
      131,
      216,
      304,
      379,
      456,
      479,
      502,
      525,
      548,
      571,
      594,
      617,
      640,
      663,
      681,
      699,
      717,
      735,
      758,
      781,
      804,
      827,
      850,
      873,
      896,
      919,
      942,
      965,
      965
    ],
    "unpinned": [
      118,
      131,
      216,
      304,
      379,
      456,
      479,
      502,
      525,
      548,
      571,
      594,
      617,
      640,
      663,
      681,
      699,
      717,
      735,
      758,
      781,
      804,
      827,
      850,
      873,
      896,
      919,
      942,
      965,
      965
    ],
    "hit": [
      102,
      115,
      188,
      269,
      338,
      410,
      433,
      456,
      479,
      502,
      525,
      548,
      571,
      594,
      617,
      635,
      653,
      671,
      689,
      712,
      735,
      758,
      781,
      804,
      827,
      850,
      873,
      896,
      919,
      919
    ],
    "assigned": [
      16,
      16,
      28,
      35,
      41,
      46,
      46,
      46,
      46,
      46,
      46,
      46,
      46,
      46,
      46,
      46,
      46,
      46,
      46,
      46,
      46,
      46,
      46,
      46,
      46,
      46,
      46,
      46,
      46,
      46
    ],
    "ratio": [
      637.500000,
      718.750000,
      671.429000,
      768.571000,
      824.390000,
      891.304000,
      941.304000,
      991.304000,
      1041.304000,
      1091.304000,
      1141.304000,
      1191.304000,
      1241.304000,
      1291.304000,
      1341.304000,
      1380.435000,
      1419.565000,
      1458.696000,
      1497.826000,
      1547.826000,
      1597.826000,
      1647.826000,
      1697.826000,
      1747.826000,
      1797.826000,
      1847.826000,
      1897.826000,
      1947.826000,
      1997.826000,
      1997.826000
    ],
    "elapsed": [
      0.001000,
      0.000000,
      0.021000,
      0.002000,
      0.003000,
      0.004000,
      0.000000,
      0.000000,
      0.000000,
      0.000000,
      0.000000,
      0.000000,
      0.000000,
      0.000000,
      0.000000,
      0.000000,
      0.000000,
      0.000000,
      0.000000,
      0.000000,
      0.000000,
      0.000000,
      0.000000,
      0.000000,
      0.000000,
      0.000000,
      0.000000,
      0.000000,
      0.000000,
      0.000000
    ]
  },
  {
    "name": "LRU-Heuristic",
    "read": [
      106,
      106,
      118,
      125,
      131,
      136,
      136,
      136,
      136,
      136,
      136,
      136,
      136,
      136,
      136,
      136,
      136,
      136,
      136,
      136,
      137,
      137,
      137,
      137,
      137,
      137,
      137,
      137,
      137,
      137
    ],
    "written": [
      4,
      5,
      253,
      258,
      281,
      319,
      320,
      321,
      322,
      323,
      324,
      325,
      326,
      327,
      328,
      331,
      334,
      337,
      340,
      344,
      347,
      348,
      349,
      350,
      351,
      352,
      353,
      354,
      355,
      356
    ],
    "pinned": [
      118,
      131,
      216,
      304,
      379,
      456,
      479,
      502,
      525,
      548,
      571,
      594,
      617,
      640,
      663,
      681,
      699,
      717,
      735,
      758,
      781,
      804,
      827,
      850,
      873,
      896,
      919,
      942,
      965,
      965
    ],
    "unpinned": [
      118,
      131,
      216,
      304,
      379,
      456,
      479,
      502,
      525,
      548,
      571,
      594,
      617,
      640,
      663,
      681,
      699,
      717,
      735,
      758,
      781,
      804,
      827,
      850,
      873,
      896,
      919,
      942,
      965,
      965
    ],
    "hit": [
      102,
      115,
      188,
      269,
      338,
      410,
      433,
      456,
      479,
      502,
      525,
      548,
      571,
      594,
      617,
      635,
      653,
      671,
      689,
      712,
      735,
      758,
      781,
      804,
      827,
      850,
      873,
      896,
      919,
      919
    ],
    "assigned": [
      16,
      16,
      28,
      35,
      41,
      46,
      46,
      46,
      46,
      46,
      46,
      46,
      46,
      46,
      46,
      46,
      46,
      46,
      46,
      46,
      46,
      46,
      46,
      46,
      46,
      46,
      46,
      46,
      46,
      46
    ],
    "ratio": [
      637.500000,
      718.750000,
      671.429000,
      768.571000,
      824.390000,
      891.304000,
      941.304000,
      991.304000,
      1041.304000,
      1091.304000,
      1141.304000,
      1191.304000,
      1241.304000,
      1291.304000,
      1341.304000,
      1380.435000,
      1419.565000,
      1458.696000,
      1497.826000,
      1547.826000,
      1597.826000,
      1647.826000,
      1697.826000,
      1747.826000,
      1797.826000,
      1847.826000,
      1897.826000,
      1947.826000,
      1997.826000,
      1997.826000
    ],
    "elapsed": [
      0.001000,
      0.000000,
      0.021000,
      0.003000,
      0.003000,
      0.004000,
      0.001000,
      0.000000,
      0.000000,
      0.000000,
      0.000000,
      0.000000,
      0.000000,
      0.000000,
      0.000000,
      0.000000,
      0.000000,
      0.000000,
      0.000000,
      0.001000,
      0.000000,
      0.000000,
      0.000000,
      0.000000,
      0.001000,
      0.000000,
      0.000000,
      0.000000,
      0.000000,
      0.000000
    ]
  },
  {
    "name": "LRUTs-Heuristic",
    "read": [
      106,
      106,
      118,
      125,
      131,
      136,
      136,
      136,
      136,
      136,
      136,
      136,
      136,
      136,
      136,
      136,
      136,
      136,
      136,
      136,
      137,
      137,
      137,
      137,
      137,
      137,
      137,
      137,
      137,
      137
    ],
    "written": [
      4,
      5,
      256,
      261,
      284,
      320,
      321,
      322,
      326,
      327,
      328,
      329,
      330,
      331,
      332,
      335,
      338,
      341,
      344,
      345,
      348,
      349,
      350,
      351,
      352,
      353,
      354,
      355,
      356,
      357
    ],
    "pinned": [
      118,
      131,
      216,
      304,
      379,
      456,
      479,
      502,
      525,
      548,
      571,
      594,
      617,
      640,
      663,
      681,
      699,
      717,
      735,
      758,
      781,
      804,
      827,
      850,
      873,
      896,
      919,
      942,
      965,
      965
    ],
    "unpinned": [
      118,
      131,
      216,
      304,
      379,
      456,
      479,
      502,
      525,
      548,
      571,
      594,
      617,
      640,
      663,
      681,
      699,
      717,
      735,
      758,
      781,
      804,
      827,
      850,
      873,
      896,
      919,
      942,
      965,
      965
    ],
    "hit": [
      102,
      115,
      188,
      269,
      338,
      410,
      433,
      456,
      479,
      502,
      525,
      548,
      571,
      594,
      617,
      635,
      653,
      671,
      689,
      712,
      735,
      758,
      781,
      804,
      827,
      850,
      873,
      896,
      919,
      919
    ],
    "assigned": [
      16,
      16,
      28,
      35,
      41,
      46,
      46,
      46,
      46,
      46,
      46,
      46,
      46,
      46,
      46,
      46,
      46,
      46,
      46,
      46,
      46,
      46,
      46,
      46,
      46,
      46,
      46,
      46,
      46,
      46
    ],
    "ratio": [
      637.500000,
      718.750000,
      671.429000,
      768.571000,
      824.390000,
      891.304000,
      941.304000,
      991.304000,
      1041.304000,
      1091.304000,
      1141.304000,
      1191.304000,
      1241.304000,
      1291.304000,
      1341.304000,
      1380.435000,
      1419.565000,
      1458.696000,
      1497.826000,
      1547.826000,
      1597.826000,
      1647.826000,
      1697.826000,
      1747.826000,
      1797.826000,
      1847.826000,
      1897.826000,
      1947.826000,
      1997.826000,
      1997.826000
    ],
    "elapsed": [
      0.002000,
      0.000000,
      0.021000,
      0.002000,
      0.003000,
      0.004000,
      0.000000,
      0.000000,
      0.000000,
      0.000000,
      0.000000,
      0.000000,
      0.000000,
      0.000000,
      0.000000,
      0.000000,
      0.000000,
      0.000000,
      0.000000,
      0.000000,
      0.000000,
      0.000000,
      0.000000,
      0.001000,
      0.001000,
      0.000000,
      0.000000,
      0.000000,
      0.000000,
      0.000000
    ]
  },
  {
    "name": "LRUUp-Heuristic",
    "read": [
      106,
      106,
      118,
      125,
      131,
      136,
      136,
      136,
      136,
      136,
      136,
      136,
      136,
      136,
      136,
      136,
      136,
      136,
      136,
      136,
      137,
      137,
      137,
      137,
      137,
      137,
      137,
      137,
      137,
      137
    ],
    "written": [
      4,
      5,
      253,
      261,
      284,
      320,
      321,
      322,
      323,
      324,
      325,
      326,
      327,
      328,
      329,
      332,
      335,
      341,
      344,
      345,
      348,
      349,
      350,
      351,
      352,
      353,
      354,
      355,
      356,
      357
    ],
    "pinned": [
      118,
      131,
      216,
      304,
      379,
      456,
      479,
      502,
      525,
      548,
      571,
      594,
      617,
      640,
      663,
      681,
      699,
      717,
      735,
      758,
      781,
      804,
      827,
      850,
      873,
      896,
      919,
      942,
      965,
      965
    ],
    "unpinned": [
      118,
      131,
      216,
      304,
      379,
      456,
      479,
      502,
      525,
      548,
      571,
      594,
      617,
      640,
      663,
      681,
      699,
      717,
      735,
      758,
      781,
      804,
      827,
      850,
      873,
      896,
      919,
      942,
      965,
      965
    ],
    "hit": [
      102,
      115,
      188,
      269,
      338,
      410,
      433,
      456,
      479,
      502,
      525,
      548,
      571,
      594,
      617,
      635,
      653,
      671,
      689,
      712,
      735,
      758,
      781,
      804,
      827,
      850,
      873,
      896,
      919,
      919
    ],
    "assigned": [
      16,
      16,
      28,
      35,
      41,
      46,
      46,
      46,
      46,
      46,
      46,
      46,
      46,
      46,
      46,
      46,
      46,
      46,
      46,
      46,
      46,
      46,
      46,
      46,
      46,
      46,
      46,
      46,
      46,
      46
    ],
    "ratio": [
      637.500000,
      718.750000,
      671.429000,
      768.571000,
      824.390000,
      891.304000,
      941.304000,
      991.304000,
      1041.304000,
      1091.304000,
      1141.304000,
      1191.304000,
      1241.304000,
      1291.304000,
      1341.304000,
      1380.435000,
      1419.565000,
      1458.696000,
      1497.826000,
      1547.826000,
      1597.826000,
      1647.826000,
      1697.826000,
      1747.826000,
      1797.826000,
      1847.826000,
      1897.826000,
      1947.826000,
      1997.826000,
      1997.826000
    ],
    "elapsed": [
      0.002000,
      0.000000,
      0.021000,
      0.003000,
      0.003000,
      0.004000,
      0.000000,
      0.000000,
      0.000000,
      0.000000,
      0.000000,
      0.000000,
      0.000000,
      0.000000,
      0.000000,
      0.000000,
      0.000000,
      0.000000,
      0.000000,
      0.001000,
      0.000000,
      0.000000,
      0.000000,
      0.000000,
      0.000000,
      0.000000,
      0.000000,
      0.000000,
      0.000000,
      0.000000
    ]
  },
  {
    "name": "Clock-Heuristic",
    "read": [
      106,
      106,
      118,
      125,
      131,
      136,
      136,
      136,
      136,
      136,
      136,
      136,
      136,
      136,
      136,
      136,
      136,
      136,
      136,
      136,
      137,
      137,
      137,
      137,
      137,
      137,
      137,
      137,
      137,
      137
    ],
    "written": [
      4,
      5,
      256,
      261,
      284,
      322,
      323,
      324,
      325,
      326,
      327,
      328,
      329,
      330,
      331,
      334,
      337,
      340,
      343,
      344,
      347,
      348,
      349,
      350,
      351,
      352,
      353,
      354,
      355,
      359
    ],
    "pinned": [
      118,
      131,
      216,
      304,
      379,
      456,
      479,
      502,
      525,
      548,
      571,
      594,
      617,
      640,
      663,
      681,
      699,
      717,
      735,
      758,
      781,
      804,
      827,
      850,
      873,
      896,
      919,
      942,
      965,
      965
    ],
    "unpinned": [
      118,
      131,
      216,
      304,
      379,
      456,
      479,
      502,
      525,
      548,
      571,
      594,
      617,
      640,
      663,
      681,
      699,
      717,
      735,
      758,
      781,
      804,
      827,
      850,
      873,
      896,
      919,
      942,
      965,
      965
    ],
    "hit": [
      102,
      115,
      188,
      269,
      338,
      410,
      433,
      456,
      479,
      502,
      525,
      548,
      571,
      594,
      617,
      635,
      653,
      671,
      689,
      712,
      735,
      758,
      781,
      804,
      827,
      850,
      873,
      896,
      919,
      919
    ],
    "assigned": [
      16,
      16,
      28,
      35,
      41,
      46,
      46,
      46,
      46,
      46,
      46,
      46,
      46,
      46,
      46,
      46,
      46,
      46,
      46,
      46,
      46,
      46,
      46,
      46,
      46,
      46,
      46,
      46,
      46,
      46
    ],
    "ratio": [
      637.500000,
      718.750000,
      671.429000,
      768.571000,
      824.390000,
      891.304000,
      941.304000,
      991.304000,
      1041.304000,
      1091.304000,
      1141.304000,
      1191.304000,
      1241.304000,
      1291.304000,
      1341.304000,
      1380.435000,
      1419.565000,
      1458.696000,
      1497.826000,
      1547.826000,
      1597.826000,
      1647.826000,
      1697.826000,
      1747.826000,
      1797.826000,
      1847.826000,
      1897.826000,
      1947.826000,
      1997.826000,
      1997.826000
    ],
    "elapsed": [
      0.001000,
      0.000000,
      0.021000,
      0.002000,
      0.013000,
      0.004000,
      0.000000,
      0.000000,
      0.000000,
      0.000000,
      0.000000,
      0.000000,
      0.000000,
      0.000000,
      0.000000,
      0.000000,
      0.000000,
      0.000000,
      0.000000,
      0.000000,
      0.000000,
      0.000000,
      0.000000,
      0.000000,
      0.000000,
      0.000000,
      0.000000,
      0.000000,
      0.000000,
      0.000000
    ]
  },
  {
    "name": "ClockUp-Heuristic",
    "read": [
      106,
      106,
      118,
      125,
      131,
      136,
      136,
      136,
      136,
      136,
      136,
      136,
      136,
      136,
      136,
      136,
      136,
      136,
      136,
      136,
      137,
      137,
      137,
      137,
      137,
      137,
      137,
      137,
      137,
      137
    ],
    "written": [
      4,
      5,
      256,
      261,
      284,
      320,
      321,
      322,
      323,
      324,
      325,
      326,
      327,
      328,
      329,
      332,
      338,
      341,
      344,
      345,
      348,
      349,
      350,
      351,
      352,
      353,
      354,
      355,
      356,
      357
    ],
    "pinned": [
      118,
      131,
      216,
      304,
      379,
      456,
      479,
      502,
      525,
      548,
      571,
      594,
      617,
      640,
      663,
      681,
      699,
      717,
      735,
      758,
      781,
      804,
      827,
      850,
      873,
      896,
      919,
      942,
      965,
      965
    ],
    "unpinned": [
      118,
      131,
      216,
      304,
      379,
      456,
      479,
      502,
      525,
      548,
      571,
      594,
      617,
      640,
      663,
      681,
      699,
      717,
      735,
      758,
      781,
      804,
      827,
      850,
      873,
      896,
      919,
      942,
      965,
      965
    ],
    "hit": [
      102,
      115,
      188,
      269,
      338,
      410,
      433,
      456,
      479,
      502,
      525,
      548,
      571,
      594,
      617,
      635,
      653,
      671,
      689,
      712,
      735,
      758,
      781,
      804,
      827,
      850,
      873,
      896,
      919,
      919
    ],
    "assigned": [
      16,
      16,
      28,
      35,
      41,
      46,
      46,
      46,
      46,
      46,
      46,
      46,
      46,
      46,
      46,
      46,
      46,
      46,
      46,
      46,
      46,
      46,
      46,
      46,
      46,
      46,
      46,
      46,
      46,
      46
    ],
    "ratio": [
      637.500000,
      718.750000,
      671.429000,
      768.571000,
      824.390000,
      891.304000,
      941.304000,
      991.304000,
      1041.304000,
      1091.304000,
      1141.304000,
      1191.304000,
      1241.304000,
      1291.304000,
      1341.304000,
      1380.435000,
      1419.565000,
      1458.696000,
      1497.826000,
      1547.826000,
      1597.826000,
      1647.826000,
      1697.826000,
      1747.826000,
      1797.826000,
      1847.826000,
      1897.826000,
      1947.826000,
      1997.826000,
      1997.826000
    ],
    "elapsed": [
      0.001000,
      0.000000,
      0.021000,
      0.002000,
      0.003000,
      0.003000,
      0.000000,
      0.000000,
      0.000000,
      0.000000,
      0.000000,
      0.000000,
      0.000000,
      0.000000,
      0.000000,
      0.000000,
      0.000000,
      0.000000,
      0.000000,
      0.001000,
      0.000000,
      0.000000,
      0.000000,
      0.000000,
      0.000000,
      0.000000,
      0.000000,
      0.000000,
      0.000000,
      0.000000
    ]
  }
]
