[
  {
    "name": "Naive-Basic",
    "read": [
      11560,
      11565,
      12784,
      12803,
      12828,
      12846,
      12853,
      12860,
      12867,
      12874,
      12881,
      12888,
      12895,
      12902,
      12909,
      12920,
      12930,
      12940,
      12950,
      12955,
      12961,
      12966,
      12971,
      12976,
      12981,
      12986,
      12991,
      12996,
      13001,
      13001
    ],
    "written": [
      4,
      5,
      6,
      7,
      8,
      9,
      10,
      11,
      12,
      13,
      14,
      15,
      16,
      17,
      18,
      21,
      24,
      27,
      30,
      31,
      34,
      35,
      36,
      37,
      38,
      39,
      40,
      41,
      42,
      43
    ],
    "pinned": [
      160,
      166,
      101385,
      101407,
      107032,
      107651,
      107658,
      107665,
      107672,
      107679,
      107686,
      107693,
      107700,
      107707,
      107714,
      107725,
      107736,
      107747,
      107758,
      107765,
      107772,
      107779,
      107786,
      107793,
      107800,
      107807,
      107814,
      107821,
      107828,
      107828
    ],
    "unpinned": [
      160,
      166,
      101385,
      101407,
      107032,
      107651,
      107658,
      107665,
      107672,
      107679,
      107686,
      107693,
      107700,
      107707,
      107714,
      107725,
      107736,
      107747,
      107758,
      107765,
      107772,
      107779,
      107786,
      107793,
      107800,
      107807,
      107814,
      107821,
      107828,
      107828
    ],
    "hit": [
      115,
      116,
      100116,
      100119,
      105719,
      106320,
      106320,
      106320,
      106320,
      106320,
      106320,
      106320,
      106320,
      106320,
      106320,
      106320,
      106321,
      106322,
      106323,
      106325,
      106327,
      106329,
      106331,
      106333,
      106335,
      106337,
      106339,
      106341,
      106343,
      106343
    ],
    "assigned": [
      45,
      50,
      1269,
      1288,
      1313,
      1331,
      1338,
      1345,
      1352,
      1359,
      1366,
      1373,
      1380,
      1387,
      1394,
      1405,
      1415,
      1425,
      1435,
      1440,
      1445,
      1450,
      1455,
      1460,
      1465,
      1470,
      1475,
      1480,
      1485,
      1485
    ],
    "ratio": [
      255.556,
      232,
      7889.361,
      7773.214,
      8051.713,
      7987.979,
      7946.188,
      7904.833,
      7863.905,
      7823.399,
      7783.309,
      7743.627,
      7704.348,
      7665.465,
      7626.973,
      7567.26,
      7513.852,
      7461.193,
      7409.268,
      7383.681,
      7358.271,
      7333.035,
      7307.973,
      7283.082,
      7258.362,
      7233.81,
      7209.424,
      7185.203,
      7161.145,
      7161.145
    ],
    "elapsed": [
      0.021,
      0.001,
      22.426,
      0.002,
      1.515,
      0.099,
      0.001,
      0.001,
      0.001,
      0.001,
      0.001,
      0.001,
      0.001,
      0.001,
      0.001,
      0.001,
      0.001,
      0.001,
      0.001,
      0.001,
      0.001,
      0.001,
      0.001,
      0.001,
      0.001,
      0.001,
      0.001,
      0.001,
      0.001,
      0
    ]
  },
  {
    "name": "NaiveUp-Basic",
    "read": [
      11560,
      11565,
      12784,
      12803,
      12828,
      12846,
      12853,
      12860,
      12867,
      12874,
      12881,
      12888,
      12895,
      12902,
      12909,
      12920,
      12931,
      12942,
      12953,
      12959,
      12966,
      12972,
      12978,
      12984,
      12990,
      12996,
      13002,
      13008,
      13014,
      13014
    ],
    "written": [
      4,
      5,
      6,
      7,
      8,
      9,
      10,
      11,
      12,
      13,
      14,
      15,
      16,
      17,
      18,
      21,
      24,
      27,
      30,
      31,
      34,
      35,
      36,
      37,
      38,
      39,
      40,
      41,
      42,
      43
    ],
    "pinned": [
      160,
      166,
      101385,
      101407,
      107032,
      107651,
      107658,
      107665,
      107672,
      107679,
      107686,
      107693,
      107700,
      107707,
      107714,
      107725,
      107736,
      107747,
      107758,
      107765,
      107772,
      107779,
      107786,
      107793,
      107800,
      107807,
      107814,
      107821,
      107828,
      107828
    ],
    "unpinned": [
      160,
      166,
      101385,
      101407,
      107032,
      107651,
      107658,
      107665,
      107672,
      107679,
      107686,
      107693,
      107700,
      107707,
      107714,
      107725,
      107736,
      107747,
      107758,
      107765,
      107772,
      107779,
      107786,
      107793,
      107800,
      107807,
      107814,
      107821,
      107828,
      107828
    ],
    "hit": [
      115,
      116,
      100116,
      100119,
      105719,
      106320,
      106320,
      106320,
      106320,
      106320,
      106320,
      106320,
      106320,
      106320,
      106320,
      106320,
      106320,
      106320,
      106320,
      106321,
      106322,
      106323,
      106324,
      106325,
      106326,
      106327,
      106328,
      106329,
      106330,
      106330
    ],
    "assigned": [
      45,
      50,
      1269,
      1288,
      1313,
      1331,
      1338,
      1345,
      1352,
      1359,
      1366,
      1373,
      1380,
      1387,
      1394,
      1405,
      1416,
      1427,
      1438,
      1444,
      1450,
      1456,
      1462,
      1468,
      1474,
      1480,
      1486,
      1492,
      1498,
      1498
    ],
    "ratio": [
      255.556,
      232,
      7889.361,
      7773.214,
      8051.713,
      7987.979,
      7946.188,
      7904.833,
      7863.905,
      7823.399,
      7783.309,
      7743.627,
      7704.348,
      7665.465,
      7626.973,
      7567.26,
      7508.475,
      7450.596,
      7393.602,
      7362.95,
      7332.552,
      7302.404,
      7272.504,
      7242.848,
      7213.433,
      7184.257,
      7155.316,
      7126.608,
      7098.131,
      7098.131
    ],
    "elapsed": [
      0.026,
      0.001,
      23.017,
      0.002,
      1.63,
      0.097,
      0.001,
      0.001,
      0.001,
      0.001,
      0.001,
      0.001,
      0.001,
      0.001,
      0.001,
      0.001,
      0.001,
      0.001,
      0.001,
      0.001,
      0.001,
      0.001,
      0.001,
      0.001,
      0.001,
      0.001,
      0.001,
      0.001,
      0.001,
      0
    ]
  },
  {
    "name": "NaiveBis-Basic",
    "read": [
      11560,
      11565,
      12784,
      12803,
      12828,
      12846,
      12853,
      12860,
      12867,
      12874,
      12881,
      12888,
      12895,
      12902,
      12909,
      12920,
      12930,
      12940,
      12950,
      12955,
      12961,
      12966,
      12971,
      12976,
      12981,
      12986,
      12991,
      12996,
      13001,
      13001
    ],
    "written": [
      4,
      5,
      6,
      7,
      8,
      9,
      10,
      11,
      12,
      13,
      14,
      15,
      16,
      17,
      18,
      21,
      24,
      27,
      30,
      31,
      34,
      35,
      36,
      37,
      38,
      39,
      40,
      41,
      42,
      43
    ],
    "pinned": [
      160,
      166,
      101385,
      101407,
      107032,
      107651,
      107658,
      107665,
      107672,
      107679,
      107686,
      107693,
      107700,
      107707,
      107714,
      107725,
      107736,
      107747,
      107758,
      107765,
      107772,
      107779,
      107786,
      107793,
      107800,
      107807,
      107814,
      107821,
      107828,
      107828
    ],
    "unpinned": [
      160,
      166,
      101385,
      101407,
      107032,
      107651,
      107658,
      107665,
      107672,
      107679,
      107686,
      107693,
      107700,
      107707,
      107714,
      107725,
      107736,
      107747,
      107758,
      107765,
      107772,
      107779,
      107786,
      107793,
      107800,
      107807,
      107814,
      107821,
      107828,
      107828
    ],
    "hit": [
      115,
      116,
      100116,
      100119,
      105719,
      106320,
      106320,
      106320,
      106320,
      106320,
      106320,
      106320,
      106320,
      106320,
      106320,
      106320,
      106321,
      106322,
      106323,
      106325,
      106327,
      106329,
      106331,
      106333,
      106335,
      106337,
      106339,
      106341,
      106343,
      106343
    ],
    "assigned": [
      45,
      50,
      1269,
      1288,
      1313,
      1331,
      1338,
      1345,
      1352,
      1359,
      1366,
      1373,
      1380,
      1387,
      1394,
      1405,
      1415,
      1425,
      1435,
      1440,
      1445,
      1450,
      1455,
      1460,
      1465,
      1470,
      1475,
      1480,
      1485,
      1485
    ],
    "ratio": [
      255.556,
      232,
      7889.361,
      7773.214,
      8051.713,
      7987.979,
      7946.188,
      7904.833,
      7863.905,
      7823.399,
      7783.309,
      7743.627,
      7704.348,
      7665.465,
      7626.973,
      7567.26,
      7513.852,
      7461.193,
      7409.268,
      7383.681,
      7358.271,
      7333.035,
      7307.973,
      7283.082,
      7258.362,
      7233.81,
      7209.424,
      7185.203,
      7161.145,
      7161.145
    ],
    "elapsed": [
      0.026,
      0.001,
      23.135,
      0.002,
      1.434,
      0.094,
      0.001,
      0.001,
      0.001,
      0.001,
      0.001,
      0.001,
      0.001,
      0.001,
      0.001,
      0.001,
      0.001,
      0.001,
      0.001,
      0.001,
      0.001,
      0.001,
      0.001,
      0.001,
      0.001,
      0.001,
      0.001,
      0.001,
      0.001,
      0
    ]
  },
  {
    "name": "NaiveBisUp-Basic",
    "read": [
      11560,
      11565,
      12784,
      12803,
      12828,
      12846,
      12853,
      12860,
      12867,
      12874,
      12881,
      12888,
      12895,
      12902,
      12909,
      12920,
      12931,
      12942,
      12953,
      12959,
      12966,
      12972,
      12978,
      12984,
      12990,
      12996,
      13002,
      13008,
      13014,
      13014
    ],
    "written": [
      4,
      5,
      6,
      7,
      8,
      9,
      10,
      11,
      12,
      13,
      14,
      15,
      16,
      17,
      18,
      21,
      24,
      27,
      30,
      31,
      34,
      35,
      36,
      37,
      38,
      39,
      40,
      41,
      42,
      43
    ],
    "pinned": [
      160,
      166,
      101385,
      101407,
      107032,
      107651,
      107658,
      107665,
      107672,
      107679,
      107686,
      107693,
      107700,
      107707,
      107714,
      107725,
      107736,
      107747,
      107758,
      107765,
      107772,
      107779,
      107786,
      107793,
      107800,
      107807,
      107814,
      107821,
      107828,
      107828
    ],
    "unpinned": [
      160,
      166,
      101385,
      101407,
      107032,
      107651,
      107658,
      107665,
      107672,
      107679,
      107686,
      107693,
      107700,
      107707,
      107714,
      107725,
      107736,
      107747,
      107758,
      107765,
      107772,
      107779,
      107786,
      107793,
      107800,
      107807,
      107814,
      107821,
      107828,
      107828
    ],
    "hit": [
      115,
      116,
      100116,
      100119,
      105719,
      106320,
      106320,
      106320,
      106320,
      106320,
      106320,
      106320,
      106320,
      106320,
      106320,
      106320,
      106320,
      106320,
      106320,
      106321,
      106322,
      106323,
      106324,
      106325,
      106326,
      106327,
      106328,
      106329,
      106330,
      106330
    ],
    "assigned": [
      45,
      50,
      1269,
      1288,
      1313,
      1331,
      1338,
      1345,
      1352,
      1359,
      1366,
      1373,
      1380,
      1387,
      1394,
      1405,
      1416,
      1427,
      1438,
      1444,
      1450,
      1456,
      1462,
      1468,
      1474,
      1480,
      1486,
      1492,
      1498,
      1498
    ],
    "ratio": [
      255.556,
      232,
      7889.361,
      7773.214,
      8051.713,
      7987.979,
      7946.188,
      7904.833,
      7863.905,
      7823.399,
      7783.309,
      7743.627,
      7704.348,
      7665.465,
      7626.973,
      7567.26,
      7508.475,
      7450.596,
      7393.602,
      7362.95,
      7332.552,
      7302.404,
      7272.504,
      7242.848,
      7213.433,
      7184.257,
      7155.316,
      7126.608,
      7098.131,
      7098.131
    ],
    "elapsed": [
      0.024,
      0.001,
      22.134,
      0.002,
      1.509,
      0.087,
      0.001,
      0.001,
      0.001,
      0.001,
      0.001,
      0.001,
      0.001,
      0.001,
      0.001,
      0.001,
      0.001,
      0.001,
      0.001,
      0.001,
      0.001,
      0.001,
      0.001,
      0.001,
      0.001,
      0.001,
      0.001,
      0.001,
      0.001,
      0
    ]
  },
  {
    "name": "FIFO-Basic",
    "read": [
      11537,
      11537,
      11537,
      11537,
      11537,
      11537,
      11537,
      11537,
      11537,
      11537,
      11537,
      11537,
      11537,
      11537,
      11537,
      11537,
      11537,
      11537,
      11537,
      11537,
      11538,
      11538,
      11538,
      11538,
      11538,
      11538,
      11538,
      11538,
      11538,
      11538
    ],
    "written": [
      4,
      5,
      6,
      7,
      8,
      9,
      10,
      11,
      12,
      13,
      14,
      15,
      16,
      17,
      18,
      21,
      24,
      27,
      30,
      31,
      34,
      35,
      36,
      37,
      38,
      39,
      40,
      41,
      42,
      43
    ],
    "pinned": [
      160,
      166,
      101385,
      101407,
      107032,
      107651,
      107658,
      107665,
      107672,
      107679,
      107686,
      107693,
      107700,
      107707,
      107714,
      107725,
      107736,
      107747,
      107758,
      107765,
      107772,
      107779,
      107786,
      107793,
      107800,
      107807,
      107814,
      107821,
      107828,
      107828
    ],
    "unpinned": [
      160,
      166,
      101385,
      101407,
      107032,
      107651,
      107658,
      107665,
      107672,
      107679,
      107686,
      107693,
      107700,
      107707,
      107714,
      107725,
      107736,
      107747,
      107758,
      107765,
      107772,
      107779,
      107786,
      107793,
      107800,
      107807,
      107814,
      107821,
      107828,
      107828
    ],
    "hit": [
      138,
      144,
      101363,
      101385,
      107010,
      107629,
      107636,
      107643,
      107650,
      107657,
      107664,
      107671,
      107678,
      107685,
      107692,
      107703,
      107714,
      107725,
      107736,
      107743,
      107750,
      107757,
      107764,
      107771,
      107778,
      107785,
      107792,
      107799,
      107806,
      107806
    ],
    "assigned": [
      22,
      22,
      22,
      22,
      22,
      22,
      22,
      22,
      22,
      22,
      22,
      22,
      22,
      22,
      22,
      22,
      22,
      22,
      22,
      22,
      22,
      22,
      22,
      22,
      22,
      22,
      22,
      22,
      22,
      22
    ],
    "ratio": [
      627.273,
      654.545,
      460740.906,
      460840.906,
      486409.094,
      489222.719,
      489254.531,
      489286.375,
      489318.156,
      489350,
      489381.844,
      489413.625,
      489445.469,
      489477.281,
      489509.094,
      489559.094,
      489609.094,
      489659.094,
      489709.094,
      489740.906,
      489772.719,
      489804.531,
      489836.375,
      489868.156,
      489900,
      489931.844,
      489963.625,
      489995.469,
      490027.281,
      490027.281
    ],
    "elapsed": [
      0.026,
      0.001,
      22.607,
      0.002,
      1.484,
      0.098,
      0.001,
      0.001,
      0.001,
      0.001,
      0.001,
      0.001,
      0.001,
      0.001,
      0.001,
      0.001,
      0.001,
      0.001,
      0.001,
      0.001,
      0.001,
      0.001,
      0.001,
      0.001,
      0.001,
      0.001,
      0.001,
      0.001,
      0.001,
      0
    ]
  },
  {
    "name": "FIFOUp-Basic",
    "read": [
      11537,
      11537,
      11537,
      11537,
      11537,
      11537,
      11537,
      11537,
      11537,
      11537,
      11537,
      11537,
      11537,
      11537,
      11537,
      11537,
      11537,
      11537,
      11537,
      11537,
      11538,
      11538,
      11538,
      11538,
      11538,
      11538,
      11538,
      11538,
      11538,
      11538
    ],
    "written": [
      4,
      5,
      6,
      7,
      8,
      9,
      10,
      11,
      12,
      13,
      14,
      15,
      16,
      17,
      18,
      21,
      24,
      27,
      30,
      31,
      34,
      35,
      36,
      37,
      38,
      39,
      40,
      41,
      42,
      43
    ],
    "pinned": [
      160,
      166,
      101385,
      101407,
      107032,
      107651,
      107658,
      107665,
      107672,
      107679,
      107686,
      107693,
      107700,
      107707,
      107714,
      107725,
      107736,
      107747,
      107758,
      107765,
      107772,
      107779,
      107786,
      107793,
      107800,
      107807,
      107814,
      107821,
      107828,
      107828
    ],
    "unpinned": [
      160,
      166,
      101385,
      101407,
      107032,
      107651,
      107658,
      107665,
      107672,
      107679,
      107686,
      107693,
      107700,
      107707,
      107714,
      107725,
      107736,
      107747,
      107758,
      107765,
      107772,
      107779,
      107786,
      107793,
      107800,
      107807,
      107814,
      107821,
      107828,
      107828
    ],
    "hit": [
      138,
      144,
      101363,
      101385,
      107010,
      107629,
      107636,
      107643,
      107650,
      107657,
      107664,
      107671,
      107678,
      107685,
      107692,
      107703,
      107714,
      107725,
      107736,
      107743,
      107750,
      107757,
      107764,
      107771,
      107778,
      107785,
      107792,
      107799,
      107806,
      107806
    ],
    "assigned": [
      22,
      22,
      22,
      22,
      22,
      22,
      22,
      22,
      22,
      22,
      22,
      22,
      22,
      22,
      22,
      22,
      22,
      22,
      22,
      22,
      22,
      22,
      22,
      22,
      22,
      22,
      22,
      22,
      22,
      22
    ],
    "ratio": [
      627.273,
      654.545,
      460740.906,
      460840.906,
      486409.094,
      489222.719,
      489254.531,
      489286.375,
      489318.156,
      489350,
      489381.844,
      489413.625,
      489445.469,
      489477.281,
      489509.094,
      489559.094,
      489609.094,
      489659.094,
      489709.094,
      489740.906,
      489772.719,
      489804.531,
      489836.375,
      489868.156,
      489900,
      489931.844,
      489963.625,
      489995.469,
      490027.281,
      490027.281
    ],
    "elapsed": [
      0.021,
      0.001,
      22.781,
      0.002,
      1.535,
      0.097,
      0.001,
      0.001,
      0.001,
      0.001,
      0.001,
      0.001,
      0.001,
      0.001,
      0.001,
      0.001,
      0.001,
      0.001,
      0.001,
      0.001,
      0.001,
      0.001,
      0.001,
      0.001,
      0.001,
      0.001,
      0.001,
      0.001,
      0.001,
      0
    ]
  },
  {
    "name": "LRU-Basic",
    "read": [
      11537,
      11537,
      11537,
      11537,
      11537,
      11537,
      11537,
      11537,
      11537,
      11537,
      11537,
      11537,
      11537,
      11537,
      11537,
      11537,
      11537,
      11537,
      11537,
      11537,
      11538,
      11538,
      11538,
      11538,
      11538,
      11538,
      11538,
      11538,
      11538,
      11538
    ],
    "written": [
      4,
      5,
      6,
      7,
      8,
      9,
      10,
      11,
      12,
      13,
      14,
      15,
      16,
      17,
      18,
      21,
      24,
      27,
      30,
      31,
      34,
      35,
      36,
      37,
      38,
      39,
      40,
      41,
      42,
      43
    ],
    "pinned": [
      160,
      166,
      101385,
      101407,
      107032,
      107651,
      107658,
      107665,
      107672,
      107679,
      107686,
      107693,
      107700,
      107707,
      107714,
      107725,
      107736,
      107747,
      107758,
      107765,
      107772,
      107779,
      107786,
      107793,
      107800,
      107807,
      107814,
      107821,
      107828,
      107828
    ],
    "unpinned": [
      160,
      166,
      101385,
      101407,
      107032,
      107651,
      107658,
      107665,
      107672,
      107679,
      107686,
      107693,
      107700,
      107707,
      107714,
      107725,
      107736,
      107747,
      107758,
      107765,
      107772,
      107779,
      107786,
      107793,
      107800,
      107807,
      107814,
      107821,
      107828,
      107828
    ],
    "hit": [
      138,
      144,
      101363,
      101385,
      107010,
      107629,
      107636,
      107643,
      107650,
      107657,
      107664,
      107671,
      107678,
      107685,
      107692,
      107703,
      107714,
      107725,
      107736,
      107743,
      107750,
      107757,
      107764,
      107771,
      107778,
      107785,
      107792,
      107799,
      107806,
      107806
    ],
    "assigned": [
      22,
      22,
      22,
      22,
      22,
      22,
      22,
      22,
      22,
      22,
      22,
      22,
      22,
      22,
      22,
      22,
      22,
      22,
      22,
      22,
      22,
      22,
      22,
      22,
      22,
      22,
      22,
      22,
      22,
      22
    ],
    "ratio": [
      627.273,
      654.545,
      460740.906,
      460840.906,
      486409.094,
      489222.719,
      489254.531,
      489286.375,
      489318.156,
      489350,
      489381.844,
      489413.625,
      489445.469,
      489477.281,
      489509.094,
      489559.094,
      489609.094,
      489659.094,
      489709.094,
      489740.906,
      489772.719,
      489804.531,
      489836.375,
      489868.156,
      489900,
      489931.844,
      489963.625,
      489995.469,
      490027.281,
      490027.281
    ],
    "elapsed": [
      0.026,
      0.001,
      22.666,
      0.002,
      1.533,
      0.098,
      0.001,
      0.001,
      0.001,
      0.001,
      0.001,
      0.001,
      0.001,
      0.001,
      0.001,
      0.002,
      0.001,
      0.001,
      0.001,
      0.001,
      0.001,
      0.001,
      0.001,
      0.001,
      0.001,
      0.001,
      0.001,
      0.001,
      0.001,
      0
    ]
  },
  {
    "name": "LRUUp-Basic",
    "read": [
      11537,
      11537,
      11537,
      11537,
      11537,
      11537,
      11537,
      11537,
      11537,
      11537,
      11537,
      11537,
      11537,
      11537,
      11537,
      11537,
      11537,
      11537,
      11537,
      11537,
      11538,
      11538,
      11538,
      11538,
      11538,
      11538,
      11538,
      11538,
      11538,
      11538
    ],
    "written": [
      4,
      5,
      6,
      7,
      8,
      9,
      10,
      11,
      12,
      13,
      14,
      15,
      16,
      17,
      18,
      21,
      24,
      27,
      30,
      31,
      34,
      35,
      36,
      37,
      38,
      39,
      40,
      41,
      42,
      43
    ],
    "pinned": [
      160,
      166,
      101385,
      101407,
      107032,
      107651,
      107658,
      107665,
      107672,
      107679,
      107686,
      107693,
      107700,
      107707,
      107714,
      107725,
      107736,
      107747,
      107758,
      107765,
      107772,
      107779,
      107786,
      107793,
      107800,
      107807,
      107814,
      107821,
      107828,
      107828
    ],
    "unpinned": [
      160,
      166,
      101385,
      101407,
      107032,
      107651,
      107658,
      107665,
      107672,
      107679,
      107686,
      107693,
      107700,
      107707,
      107714,
      107725,
      107736,
      107747,
      107758,
      107765,
      107772,
      107779,
      107786,
      107793,
      107800,
      107807,
      107814,
      107821,
      107828,
      107828
    ],
    "hit": [
      138,
      144,
      101363,
      101385,
      107010,
      107629,
      107636,
      107643,
      107650,
      107657,
      107664,
      107671,
      107678,
      107685,
      107692,
      107703,
      107714,
      107725,
      107736,
      107743,
      107750,
      107757,
      107764,
      107771,
      107778,
      107785,
      107792,
      107799,
      107806,
      107806
    ],
    "assigned": [
      22,
      22,
      22,
      22,
      22,
      22,
      22,
      22,
      22,
      22,
      22,
      22,
      22,
      22,
      22,
      22,
      22,
      22,
      22,
      22,
      22,
      22,
      22,
      22,
      22,
      22,
      22,
      22,
      22,
      22
    ],
    "ratio": [
      627.273,
      654.545,
      460740.906,
      460840.906,
      486409.094,
      489222.719,
      489254.531,
      489286.375,
      489318.156,
      489350,
      489381.844,
      489413.625,
      489445.469,
      489477.281,
      489509.094,
      489559.094,
      489609.094,
      489659.094,
      489709.094,
      489740.906,
      489772.719,
      489804.531,
      489836.375,
      489868.156,
      489900,
      489931.844,
      489963.625,
      489995.469,
      490027.281,
      490027.281
    ],
    "elapsed": [
      0.022,
      0.001,
      23.523,
      0.002,
      1.602,
      0.105,
      0.001,
      0.001,
      0.001,
      0.001,
      0.001,
      0.001,
      0.001,
      0.001,
      0.001,
      0.001,
      0.001,
      0.001,
      0.001,
      0.001,
      0.001,
      0.001,
      0.001,
      0.001,
      0.001,
      0.001,
      0.001,
      0.001,
      0.001,
      0
    ]
  },
  {
    "name": "Clock-Basic",
    "read": [
      11537,
      11537,
      11537,
      11537,
      11537,
      11537,
      11537,
      11537,
      11537,
      11537,
      11537,
      11537,
      11537,
      11537,
      11537,
      11537,
      11537,
      11537,
      11537,
      11537,
      11538,
      11538,
      11538,
      11538,
      11538,
      11538,
      11538,
      11538,
      11538,
      11538
    ],
    "written": [
      4,
      5,
      6,
      7,
      8,
      9,
      10,
      11,
      12,
      13,
      14,
      15,
      16,
      17,
      18,
      21,
      24,
      27,
      30,
      31,
      34,
      35,
      36,
      37,
      38,
      39,
      40,
      41,
      42,
      43
    ],
    "pinned": [
      160,
      166,
      101385,
      101407,
      107032,
      107651,
      107658,
      107665,
      107672,
      107679,
      107686,
      107693,
      107700,
      107707,
      107714,
      107725,
      107736,
      107747,
      107758,
      107765,
      107772,
      107779,
      107786,
      107793,
      107800,
      107807,
      107814,
      107821,
      107828,
      107828
    ],
    "unpinned": [
      160,
      166,
      101385,
      101407,
      107032,
      107651,
      107658,
      107665,
      107672,
      107679,
      107686,
      107693,
      107700,
      107707,
      107714,
      107725,
      107736,
      107747,
      107758,
      107765,
      107772,
      107779,
      107786,
      107793,
      107800,
      107807,
      107814,
      107821,
      107828,
      107828
    ],
    "hit": [
      138,
      144,
      101363,
      101385,
      107010,
      107629,
      107636,
      107643,
      107650,
      107657,
      107664,
      107671,
      107678,
      107685,
      107692,
      107703,
      107714,
      107725,
      107736,
      107743,
      107750,
      107757,
      107764,
      107771,
      107778,
      107785,
      107792,
      107799,
      107806,
      107806
    ],
    "assigned": [
      22,
      22,
      22,
      22,
      22,
      22,
      22,
      22,
      22,
      22,
      22,
      22,
      22,
      22,
      22,
      22,
      22,
      22,
      22,
      22,
      22,
      22,
      22,
      22,
      22,
      22,
      22,
      22,
      22,
      22
    ],
    "ratio": [
      627.273,
      654.545,
      460740.906,
      460840.906,
      486409.094,
      489222.719,
      489254.531,
      489286.375,
      489318.156,
      489350,
      489381.844,
      489413.625,
      489445.469,
      489477.281,
      489509.094,
      489559.094,
      489609.094,
      489659.094,
      489709.094,
      489740.906,
      489772.719,
      489804.531,
      489836.375,
      489868.156,
      489900,
      489931.844,
      489963.625,
      489995.469,
      490027.281,
      490027.281
    ],
    "elapsed": [
      0.021,
      0.001,
      23.139,
      0.002,
      1.503,
      0.099,
      0.001,
      0.001,
      0.001,
      0.001,
      0.001,
      0.001,
      0.001,
      0.001,
      0.001,
      0.001,
      0.001,
      0.001,
      0.001,
      0.001,
      0.001,
      0.001,
      0.001,
      0.001,
      0.001,
      0.001,
      0.001,
      0.001,
      0.001,
      0
    ]
  },
  {
    "name": "ClockUp-Basic",
    "read": [
      11537,
      11537,
      11537,
      11537,
      11537,
      11537,
      11537,
      11537,
      11537,
      11537,
      11537,
      11537,
      11537,
      11537,
      11537,
      11537,
      11537,
      11537,
      11537,
      11537,
      11538,
      11538,
      11538,
      11538,
      11538,
      11538,
      11538,
      11538,
      11538,
      11538
    ],
    "written": [
      4,
      5,
      6,
      7,
      8,
      9,
      10,
      11,
      12,
      13,
      14,
      15,
      16,
      17,
      18,
      21,
      24,
      27,
      30,
      31,
      34,
      35,
      36,
      37,
      38,
      39,
      40,
      41,
      42,
      43
    ],
    "pinned": [
      160,
      166,
      101385,
      101407,
      107032,
      107651,
      107658,
      107665,
      107672,
      107679,
      107686,
      107693,
      107700,
      107707,
      107714,
      107725,
      107736,
      107747,
      107758,
      107765,
      107772,
      107779,
      107786,
      107793,
      107800,
      107807,
      107814,
      107821,
      107828,
      107828
    ],
    "unpinned": [
      160,
      166,
      101385,
      101407,
      107032,
      107651,
      107658,
      107665,
      107672,
      107679,
      107686,
      107693,
      107700,
      107707,
      107714,
      107725,
      107736,
      107747,
      107758,
      107765,
      107772,
      107779,
      107786,
      107793,
      107800,
      107807,
      107814,
      107821,
      107828,
      107828
    ],
    "hit": [
      138,
      144,
      101363,
      101385,
      107010,
      107629,
      107636,
      107643,
      107650,
      107657,
      107664,
      107671,
      107678,
      107685,
      107692,
      107703,
      107714,
      107725,
      107736,
      107743,
      107750,
      107757,
      107764,
      107771,
      107778,
      107785,
      107792,
      107799,
      107806,
      107806
    ],
    "assigned": [
      22,
      22,
      22,
      22,
      22,
      22,
      22,
      22,
      22,
      22,
      22,
      22,
      22,
      22,
      22,
      22,
      22,
      22,
      22,
      22,
      22,
      22,
      22,
      22,
      22,
      22,
      22,
      22,
      22,
      22
    ],
    "ratio": [
      627.273,
      654.545,
      460740.906,
      460840.906,
      486409.094,
      489222.719,
      489254.531,
      489286.375,
      489318.156,
      489350,
      489381.844,
      489413.625,
      489445.469,
      489477.281,
      489509.094,
      489559.094,
      489609.094,
      489659.094,
      489709.094,
      489740.906,
      489772.719,
      489804.531,
      489836.375,
      489868.156,
      489900,
      489931.844,
      489963.625,
      489995.469,
      490027.281,
      490027.281
    ],
    "elapsed": [
      0.021,
      0.001,
      22.736,
      0.002,
      1.526,
      0.095,
      0.001,
      0.001,
      0.001,
      0.001,
      0.001,
      0.001,
      0.001,
      0.001,
      0.001,
      0.001,
      0.001,
      0.001,
      0.001,
      0.001,
      0.001,
      0.001,
      0.001,
      0.001,
      0.001,
      0.001,
      0.001,
      0.001,
      0.001,
      0
    ]
  },
  {
    "name": "Naive-Heuristic",
    "read": [
      11583,
      11590,
      11708,
      11925,
      11962,
      11999,
      12013,
      12025,
      12037,
      12049,
      12061,
      12073,
      12085,
      12097,
      12109,
      12119,
      12129,
      12139,
      12149,
      12161,
      12174,
      12186,
      12198,
      12210,
      12222,
      12234,
      12246,
      12258,
      12270,
      12270
    ],
    "written": [
      4,
      5,
      961,
      979,
      1005,
      1068,
      1069,
      1070,
      1071,
      1075,
      1076,
      1077,
      1078,
      1079,
      1080,
      1083,
      1086,
      1089,
      1092,
      1093,
      1096,
      1097,
      1098,
      1099,
      1100,
      1101,
      1102,
      1103,
      1104,
      1105
    ],
    "pinned": [
      174,
      181,
      308,
      614,
      666,
      807,
      821,
      835,
      849,
      863,
      877,
      891,
      905,
      919,
      933,
      944,
      955,
      966,
      977,
      991,
      1005,
      1019,
      1033,
      1047,
      1061,
      1075,
      1089,
      1103,
      1117,
      1117
    ],
    "unpinned": [
      174,
      181,
      308,
      614,
      666,
      807,
      821,
      835,
      849,
      863,
      877,
      891,
      905,
      919,
      933,
      944,
      955,
      966,
      977,
      991,
      1005,
      1019,
      1033,
      1047,
      1061,
      1075,
      1089,
      1103,
      1117,
      1117
    ],
    "hit": [
      106,
      106,
      115,
      204,
      219,
      323,
      323,
      325,
      327,
      329,
      331,
      333,
      335,
      337,
      339,
      340,
      341,
      342,
      343,
      345,
      347,
      349,
      351,
      353,
      355,
      357,
      359,
      361,
      363,
      363
    ],
    "assigned": [
      68,
      75,
      193,
      410,
      447,
      484,
      498,
      510,
      522,
      534,
      546,
      558,
      570,
      582,
      594,
      604,
      614,
      624,
      634,
      646,
      658,
      670,
      682,
      694,
      706,
      718,
      730,
      742,
      754,
      754
    ],
    "ratio": [
      155.882,
      141.333,
      59.585,
      49.756,
      48.993,
      66.736,
      64.859,
      63.725,
      62.644,
      61.61,
      60.623,
      59.677,
      58.772,
      57.904,
      57.071,
      56.291,
      55.537,
      54.808,
      54.101,
      53.406,
      52.736,
      52.09,
      51.466,
      50.865,
      50.283,
      49.721,
      49.178,
      48.652,
      48.143,
      48.143
    ],
    "elapsed": [
      0.009,
      0.001,
      1.071,
      0.018,
      0.01,
      0.036,
      0.002,
      0.002,
      0.001,
      0.002,
      0.002,
      0.002,
      0.002,
      0.002,
      0.002,
      0.002,
      0.001,
      0.001,
      0.001,
      0.002,
      0.002,
      0.002,
      0.002,
      0.002,
      0.002,
      0.002,
      0.002,
      0.002,
      0.002,
      0
    ]
  },
  {
    "name": "NaiveUp-Heuristic",
    "read": [
      11583,
      11590,
      11671,
      11887,
      11922,
      11953,
      11966,
      11977,
      11988,
      11999,
      12010,
      12021,
      12032,
      12043,
      12054,
      12063,
      12072,
      12081,
      12090,
      12101,
      12113,
      12124,
      12135,
      12146,
      12157,
      12168,
      12179,
      12190,
      12201,
      12201
    ],
    "written": [
      4,
      5,
      924,
      942,
      965,
      1026,
      1027,
      1028,
      1029,
      1033,
      1034,
      1035,
      1036,
      1037,
      1038,
      1041,
      1044,
      1047,
      1050,
      1051,
      1054,
      1055,
      1056,
      1057,
      1058,
      1059,
      1060,
      1061,
      1062,
      1063
    ],
    "pinned": [
      174,
      181,
      308,
      614,
      666,
      807,
      821,
      835,
      849,
      863,
      877,
      891,
      905,
      919,
      933,
      944,
      955,
      966,
      977,
      991,
      1005,
      1019,
      1033,
      1047,
      1061,
      1075,
      1089,
      1103,
      1117,
      1117
    ],
    "unpinned": [
      174,
      181,
      308,
      614,
      666,
      807,
      821,
      835,
      849,
      863,
      877,
      891,
      905,
      919,
      933,
      944,
      955,
      966,
      977,
      991,
      1005,
      1019,
      1033,
      1047,
      1061,
      1075,
      1089,
      1103,
      1117,
      1117
    ],
    "hit": [
      106,
      106,
      152,
      242,
      259,
      369,
      370,
      373,
      376,
      379,
      382,
      385,
      388,
      391,
      394,
      396,
      398,
      400,
      402,
      405,
      408,
      411,
      414,
      417,
      420,
      423,
      426,
      429,
      432,
      432
    ],
    "assigned": [
      68,
      75,
      156,
      372,
      407,
      438,
      451,
      462,
      473,
      484,
      495,
      506,
      517,
      528,
      539,
      548,
      557,
      566,
      575,
      586,
      597,
      608,
      619,
      630,
      641,
      652,
      663,
      674,
      685,
      685
    ],
    "ratio": [
      155.882,
      141.333,
      97.436,
      65.054,
      63.636,
      84.247,
      82.04,
      80.736,
      79.493,
      78.306,
      77.172,
      76.087,
      75.048,
      74.053,
      73.098,
      72.263,
      71.454,
      70.671,
      69.913,
      69.113,
      68.342,
      67.599,
      66.882,
      66.19,
      65.523,
      64.877,
      64.253,
      63.65,
      63.066,
      63.066
    ],
    "elapsed": [
      0.011,
      0.001,
      1.114,
      0.026,
      0.011,
      0.038,
      0.002,
      0.002,
      0.002,
      0.002,
      0.002,
      0.002,
      0.002,
      0.002,
      0.002,
      0.002,
      0.001,
      0.001,
      0.001,
      0.002,
      0.002,
      0.002,
      0.002,
      0.002,
      0.002,
      0.002,
      0.002,
      0.002,
      0.002,
      0
    ]
  },
  {
    "name": "NaiveBis-Heuristic",
    "read": [
      11583,
      11590,
      11708,
      11925,
      11962,
      11999,
      12013,
      12025,
      12037,
      12049,
      12061,
      12073,
      12085,
      12097,
      12109,
      12119,
      12129,
      12139,
      12149,
      12161,
      12174,
      12186,
      12198,
      12210,
      12222,
      12234,
      12246,
      12258,
      12270,
      12270
    ],
    "written": [
      4,
      5,
      961,
      979,
      1005,
      1068,
      1069,
      1070,
      1071,
      1075,
      1076,
      1077,
      1078,
      1079,
      1080,
      1083,
      1086,
      1089,
      1092,
      1093,
      1096,
      1097,
      1098,
      1099,
      1100,
      1101,
      1102,
      1103,
      1104,
      1105
    ],
    "pinned": [
      174,
      181,
      308,
      614,
      666,
      807,
      821,
      835,
      849,
      863,
      877,
      891,
      905,
      919,
      933,
      944,
      955,
      966,
      977,
      991,
      1005,
      1019,
      1033,
      1047,
      1061,
      1075,
      1089,
      1103,
      1117,
      1117
    ],
    "unpinned": [
      174,
      181,
      308,
      614,
      666,
      807,
      821,
      835,
      849,
      863,
      877,
      891,
      905,
      919,
      933,
      944,
      955,
      966,
      977,
      991,
      1005,
      1019,
      1033,
      1047,
      1061,
      1075,
      1089,
      1103,
      1117,
      1117
    ],
    "hit": [
      106,
      106,
      115,
      204,
      219,
      323,
      323,
      325,
      327,
      329,
      331,
      333,
      335,
      337,
      339,
      340,
      341,
      342,
      343,
      345,
      347,
      349,
      351,
      353,
      355,
      357,
      359,
      361,
      363,
      363
    ],
    "assigned": [
      68,
      75,
      193,
      410,
      447,
      484,
      498,
      510,
      522,
      534,
      546,
      558,
      570,
      582,
      594,
      604,
      614,
      624,
      634,
      646,
      658,
      670,
      682,
      694,
      706,
      718,
      730,
      742,
      754,
      754
    ],
    "ratio": [
      155.882,
      141.333,
      59.585,
      49.756,
      48.993,
      66.736,
      64.859,
      63.725,
      62.644,
      61.61,
      60.623,
      59.677,
      58.772,
      57.904,
      57.071,
      56.291,
      55.537,
      54.808,
      54.101,
      53.406,
      52.736,
      52.09,
      51.466,
      50.865,
      50.283,
      49.721,
      49.178,
      48.652,
      48.143,
      48.143
    ],
    "elapsed": [
      0.009,
      0.001,
      1.104,
      0.017,
      0.011,
      0.037,
      0.002,
      0.002,
      0.002,
      0.002,
      0.002,
      0.002,
      0.002,
      0.002,
      0.002,
      0.001,
      0.001,
      0.001,
      0.001,
      0.002,
      0.002,
      0.002,
      0.002,
      0.002,
      0.002,
      0.002,
      0.002,
      0.002,
      0.002,
      0
    ]
  },
  {
    "name": "NaiveBisUp-Heuristic",
    "read": [
      11583,
      11590,
      11671,
      11887,
      11922,
      11953,
      11966,
      11977,
      11988,
      11999,
      12010,
      12021,
      12032,
      12043,
      12054,
      12063,
      12072,
      12081,
      12090,
      12101,
      12113,
      12124,
      12135,
      12146,
      12157,
      12168,
      12179,
      12190,
      12201,
      12201
    ],
    "written": [
      4,
      5,
      924,
      942,
      965,
      1026,
      1027,
      1028,
      1029,
      1033,
      1034,
      1035,
      1036,
      1037,
      1038,
      1041,
      1044,
      1047,
      1050,
      1051,
      1054,
      1055,
      1056,
      1057,
      1058,
      1059,
      1060,
      1061,
      1062,
      1063
    ],
    "pinned": [
      174,
      181,
      308,
      614,
      666,
      807,
      821,
      835,
      849,
      863,
      877,
      891,
      905,
      919,
      933,
      944,
      955,
      966,
      977,
      991,
      1005,
      1019,
      1033,
      1047,
      1061,
      1075,
      1089,
      1103,
      1117,
      1117
    ],
    "unpinned": [
      174,
      181,
      308,
      614,
      666,
      807,
      821,
      835,
      849,
      863,
      877,
      891,
      905,
      919,
      933,
      944,
      955,
      966,
      977,
      991,
      1005,
      1019,
      1033,
      1047,
      1061,
      1075,
      1089,
      1103,
      1117,
      1117
    ],
    "hit": [
      106,
      106,
      152,
      242,
      259,
      369,
      370,
      373,
      376,
      379,
      382,
      385,
      388,
      391,
      394,
      396,
      398,
      400,
      402,
      405,
      408,
      411,
      414,
      417,
      420,
      423,
      426,
      429,
      432,
      432
    ],
    "assigned": [
      68,
      75,
      156,
      372,
      407,
      438,
      451,
      462,
      473,
      484,
      495,
      506,
      517,
      528,
      539,
      548,
      557,
      566,
      575,
      586,
      597,
      608,
      619,
      630,
      641,
      652,
      663,
      674,
      685,
      685
    ],
    "ratio": [
      155.882,
      141.333,
      97.436,
      65.054,
      63.636,
      84.247,
      82.04,
      80.736,
      79.493,
      78.306,
      77.172,
      76.087,
      75.048,
      74.053,
      73.098,
      72.263,
      71.454,
      70.671,
      69.913,
      69.113,
      68.342,
      67.599,
      66.882,
      66.19,
      65.523,
      64.877,
      64.253,
      63.65,
      63.066,
      63.066
    ],
    "elapsed": [
      0.009,
      0.001,
      1.108,
      0.014,
      0.009,
      0.038,
      0.002,
      0.001,
      0.001,
      0.001,
      0.001,
      0.001,
      0.001,
      0.001,
      0.001,
      0.001,
      0.001,
      0.001,
      0.001,
      0.002,
      0.001,
      0.002,
      0.001,
      0.001,
      0.001,
      0.001,
      0.001,
      0.001,
      0.001,
      0
    ]
  },
  {
    "name": "FIFO-Heuristic",
    "read": [
      11539,
      11539,
      11579,
      11608,
      11621,
      11628,
      11628,
      11628,
      11628,
      11628,
      11628,
      11628,
      11628,
      11628,
      11628,
      11628,
      11628,
      11628,
      11628,
      11628,
      11629,
      11629,
      11629,
      11629,
      11629,
      11629,
      11629,
      11629,
      11629,
      11629
    ],
    "written": [
      4,
      5,
      924,
      942,
      965,
      1027,
      1028,
      1029,
      1030,
      1034,
      1035,
      1036,
      1037,
      1038,
      1039,
      1042,
      1045,
      1048,
      1051,
      1052,
      1055,
      1056,
      1057,
      1058,
      1059,
      1060,
      1061,
      1062,
      1063,
      1064
    ],
    "pinned": [
      174,
      181,
      308,
      614,
      666,
      807,
      821,
      835,
      849,
      863,
      877,
      891,
      905,
      919,
      933,
      944,
      955,
      966,
      977,
      991,
      1005,
      1019,
      1033,
      1047,
      1061,
      1075,
      1089,
      1103,
      1117,
      1117
    ],
    "unpinned": [
      174,
      181,
      308,
      614,
      666,
      807,
      821,
      835,
      849,
      863,
      877,
      891,
      905,
      919,
      933,
      944,
      955,
      966,
      977,
      991,
      1005,
      1019,
      1033,
      1047,
      1061,
      1075,
      1089,
      1103,
      1117,
      1117
    ],
    "hit": [
      150,
      157,
      244,
      521,
      560,
      694,
      708,
      722,
      736,
      750,
      764,
      778,
      792,
      806,
      820,
      831,
      842,
      853,
      864,
      878,
      892,
      906,
      920,
      934,
      948,
      962,
      976,
      990,
      1004,
      1004
    ],
    "assigned": [
      24,
      24,
      64,
      93,
      106,
      113,
      113,
      113,
      113,
      113,
      113,
      113,
      113,
      113,
      113,
      113,
      113,
      113,
      113,
      113,
      113,
      113,
      113,
      113,
      113,
      113,
      113,
      113,
      113,
      113
    ],
    "ratio": [
      625,
      654.167,
      381.25,
      560.215,
      528.302,
      614.159,
      626.549,
      638.938,
      651.327,
      663.717,
      676.106,
      688.496,
      700.885,
      713.274,
      725.664,
      735.398,
      745.133,
      754.867,
      764.602,
      776.991,
      789.381,
      801.77,
      814.159,
      826.549,
      838.938,
      851.327,
      863.717,
      876.106,
      888.496,
      888.496
    ],
    "elapsed": [
      0.011,
      0.001,
      1.073,
      0.014,
      0.01,
      0.035,
      0.002,
      0.001,
      0.001,
      0.001,
      0.001,
      0.001,
      0.001,
      0.001,
      0.001,
      0.001,
      0.001,
      0.001,
      0.001,
      0.002,
      0.001,
      0.001,
      0.001,
      0.001,
      0.001,
      0.001,
      0.001,
      0.001,
      0.001,
      0
    ]
  },
  {
    "name": "FIFOUp-Heuristic",
    "read": [
      11539,
      11539,
      11579,
      11608,
      11621,
      11628,
      11628,
      11628,
      11628,
      11628,
      11628,
      11628,
      11628,
      11628,
      11628,
      11628,
      11628,
      11628,
      11628,
      11628,
      11629,
      11629,
      11629,
      11629,
      11629,
      11629,
      11629,
      11629,
      11629,
      11629
    ],
    "written": [
      4,
      5,
      924,
      942,
      965,
      1027,
      1028,
      1029,
      1030,
      1034,
      1035,
      1036,
      1037,
      1038,
      1039,
      1042,
      1045,
      1048,
      1051,
      1052,
      1055,
      1056,
      1057,
      1058,
      1059,
      1060,
      1061,
      1062,
      1063,
      1064
    ],
    "pinned": [
      174,
      181,
      308,
      614,
      666,
      807,
      821,
      835,
      849,
      863,
      877,
      891,
      905,
      919,
      933,
      944,
      955,
      966,
      977,
      991,
      1005,
      1019,
      1033,
      1047,
      1061,
      1075,
      1089,
      1103,
      1117,
      1117
    ],
    "unpinned": [
      174,
      181,
      308,
      614,
      666,
      807,
      821,
      835,
      849,
      863,
      877,
      891,
      905,
      919,
      933,
      944,
      955,
      966,
      977,
      991,
      1005,
      1019,
      1033,
      1047,
      1061,
      1075,
      1089,
      1103,
      1117,
      1117
    ],
    "hit": [
      150,
      157,
      244,
      521,
      560,
      694,
      708,
      722,
      736,
      750,
      764,
      778,
      792,
      806,
      820,
      831,
      842,
      853,
      864,
      878,
      892,
      906,
      920,
      934,
      948,
      962,
      976,
      990,
      1004,
      1004
    ],
    "assigned": [
      24,
      24,
      64,
      93,
      106,
      113,
      113,
      113,
      113,
      113,
      113,
      113,
      113,
      113,
      113,
      113,
      113,
      113,
      113,
      113,
      113,
      113,
      113,
      113,
      113,
      113,
      113,
      113,
      113,
      113
    ],
    "ratio": [
      625,
      654.167,
      381.25,
      560.215,
      528.302,
      614.159,
      626.549,
      638.938,
      651.327,
      663.717,
      676.106,
      688.496,
      700.885,
      713.274,
      725.664,
      735.398,
      745.133,
      754.867,
      764.602,
      776.991,
      789.381,
      801.77,
      814.159,
      826.549,
      838.938,
      851.327,
      863.717,
      876.106,
      888.496,
      888.496
    ],
    "elapsed": [
      0.012,
      0.001,
      1,
      0.014,
      0.009,
      0.033,
      0.001,
      0.002,
      0.002,
      0.002,
      0.002,
      0.001,
      0.001,
      0.001,
      0.001,
      0.001,
      0.001,
      0.001,
      0.001,
      0.002,
      0.001,
      0.002,
      0.001,
      0.001,
      0.001,
      0.002,
      0.001,
      0.001,
      0.001,
      0
    ]
  },
  {
    "name": "LRU-Heuristic",
    "read": [
      11539,
      11539,
      11579,
      11596,
      11604,
      11611,
      11611,
      11611,
      11611,
      11611,
      11611,
      11611,
      11611,
      11611,
      11611,
      11611,
      11611,
      11611,
      11611,
      11611,
      11612,
      11612,
      11612,
      11612,
      11612,
      11612,
      11612,
      11612,
      11612,
      11612
    ],
    "written": [
      4,
      5,
      924,
      942,
      965,
      1027,
      1028,
      1029,
      1030,
      1034,
      1035,
      1036,
      1037,
      1038,
      1039,
      1042,
      1045,
      1048,
      1051,
      1052,
      1055,
      1056,
      1057,
      1058,
      1059,
      1060,
      1061,
      1062,
      1063,
      1064
    ],
    "pinned": [
      174,
      181,
      308,
      614,
      666,
      807,
      821,
      835,
      849,
      863,
      877,
      891,
      905,
      919,
      933,
      944,
      955,
      966,
      977,
      991,
      1005,
      1019,
      1033,
      1047,
      1061,
      1075,
      1089,
      1103,
      1117,
      1117
    ],
    "unpinned": [
      174,
      181,
      308,
      614,
      666,
      807,
      821,
      835,
      849,
      863,
      877,
      891,
      905,
      919,
      933,
      944,
      955,
      966,
      977,
      991,
      1005,
      1019,
      1033,
      1047,
      1061,
      1075,
      1089,
      1103,
      1117,
      1117
    ],
    "hit": [
      150,
      157,
      244,
      533,
      577,
      711,
      725,
      739,
      753,
      767,
      781,
      795,
      809,
      823,
      837,
      848,
      859,
      870,
      881,
      895,
      909,
      923,
      937,
      951,
      965,
      979,
      993,
      1007,
      1021,
      1021
    ],
    "assigned": [
      24,
      24,
      64,
      81,
      89,
      96,
      96,
      96,
      96,
      96,
      96,
      96,
      96,
      96,
      96,
      96,
      96,
      96,
      96,
      96,
      96,
      96,
      96,
      96,
      96,
      96,
      96,
      96,
      96,
      96
    ],
    "ratio": [
      625,
      654.167,
      381.25,
      658.025,
      648.315,
      740.625,
      755.208,
      769.792,
      784.375,
      798.958,
      813.542,
      828.125,
      842.708,
      857.292,
      871.875,
      883.333,
      894.792,
      906.25,
      917.708,
      932.292,
      946.875,
      961.458,
      976.042,
      990.625,
      1005.208,
      1019.792,
      1034.375,
      1048.958,
      1063.542,
      1063.542
    ],
    "elapsed": [
      0.015,
      0.002,
      1.234,
      0.018,
      0.013,
      0.038,
      0.002,
      0.002,
      0.002,
      0.002,
      0.002,
      0.002,
      0.002,
      0.002,
      0.002,
      0.002,
      0.002,
      0.002,
      0.002,
      0.002,
      0.002,
      0.002,
      0.002,
      0.002,
      0.002,
      0.002,
      0.002,
      0.002,
      0.002,
      0
    ]
  },
  {
    "name": "LRUUp-Heuristic",
    "read": [
      11539,
      11539,
      11579,
      11596,
      11604,
      11611,
      11611,
      11611,
      11611,
      11611,
      11611,
      11611,
      11611,
      11611,
      11611,
      11611,
      11611,
      11611,
      11611,
      11611,
      11612,
      11612,
      11612,
      11612,
      11612,
      11612,
      11612,
      11612,
      11612,
      11612
    ],
    "written": [
      4,
      5,
      924,
      942,
      965,
      1027,
      1028,
      1029,
      1030,
      1034,
      1035,
      1036,
      1037,
      1038,
      1039,
      1042,
      1045,
      1048,
      1051,
      1052,
      1055,
      1056,
      1057,
      1058,
      1059,
      1060,
      1061,
      1062,
      1063,
      1064
    ],
    "pinned": [
      174,
      181,
      308,
      614,
      666,
      807,
      821,
      835,
      849,
      863,
      877,
      891,
      905,
      919,
      933,
      944,
      955,
      966,
      977,
      991,
      1005,
      1019,
      1033,
      1047,
      1061,
      1075,
      1089,
      1103,
      1117,
      1117
    ],
    "unpinned": [
      174,
      181,
      308,
      614,
      666,
      807,
      821,
      835,
      849,
      863,
      877,
      891,
      905,
      919,
      933,
      944,
      955,
      966,
      977,
      991,
      1005,
      1019,
      1033,
      1047,
      1061,
      1075,
      1089,
      1103,
      1117,
      1117
    ],
    "hit": [
      150,
      157,
      244,
      533,
      577,
      711,
      725,
      739,
      753,
      767,
      781,
      795,
      809,
      823,
      837,
      848,
      859,
      870,
      881,
      895,
      909,
      923,
      937,
      951,
      965,
      979,
      993,
      1007,
      1021,
      1021
    ],
    "assigned": [
      24,
      24,
      64,
      81,
      89,
      96,
      96,
      96,
      96,
      96,
      96,
      96,
      96,
      96,
      96,
      96,
      96,
      96,
      96,
      96,
      96,
      96,
      96,
      96,
      96,
      96,
      96,
      96,
      96,
      96
    ],
    "ratio": [
      625,
      654.167,
      381.25,
      658.025,
      648.315,
      740.625,
      755.208,
      769.792,
      784.375,
      798.958,
      813.542,
      828.125,
      842.708,
      857.292,
      871.875,
      883.333,
      894.792,
      906.25,
      917.708,
      932.292,
      946.875,
      961.458,
      976.042,
      990.625,
      1005.208,
      1019.792,
      1034.375,
      1048.958,
      1063.542,
      1063.542
    ],
    "elapsed": [
      0.012,
      0.001,
      1.028,
      0.016,
      0.009,
      0.034,
      0.002,
      0.001,
      0.001,
      0.001,
      0.001,
      0.001,
      0.001,
      0.001,
      0.001,
      0.001,
      0.001,
      0.001,
      0.001,
      0.002,
      0.001,
      0.001,
      0.001,
      0.002,
      0.003,
      0.001,
      0.001,
      0.001,
      0.001,
      0
    ]
  },
  {
    "name": "Clock-Heuristic",
    "read": [
      11539,
      11539,
      11579,
      11607,
      11619,
      11626,
      11626,
      11626,
      11626,
      11626,
      11626,
      11626,
      11626,
      11626,
      11626,
      11626,
      11626,
      11626,
      11626,
      11626,
      11627,
      11627,
      11627,
      11627,
      11627,
      11627,
      11627,
      11627,
      11627,
      11627
    ],
    "written": [
      4,
      5,
      924,
      942,
      965,
      1027,
      1028,
      1029,
      1030,
      1034,
      1035,
      1036,
      1037,
      1038,
      1039,
      1042,
      1045,
      1048,
      1051,
      1052,
      1055,
      1056,
      1057,
      1058,
      1059,
      1060,
      1061,
      1062,
      1063,
      1064
    ],
    "pinned": [
      174,
      181,
      308,
      614,
      666,
      807,
      821,
      835,
      849,
      863,
      877,
      891,
      905,
      919,
      933,
      944,
      955,
      966,
      977,
      991,
      1005,
      1019,
      1033,
      1047,
      1061,
      1075,
      1089,
      1103,
      1117,
      1117
    ],
    "unpinned": [
      174,
      181,
      308,
      614,
      666,
      807,
      821,
      835,
      849,
      863,
      877,
      891,
      905,
      919,
      933,
      944,
      955,
      966,
      977,
      991,
      1005,
      1019,
      1033,
      1047,
      1061,
      1075,
      1089,
      1103,
      1117,
      1117
    ],
    "hit": [
      150,
      157,
      244,
      522,
      562,
      696,
      710,
      724,
      738,
      752,
      766,
      780,
      794,
      808,
      822,
      833,
      844,
      855,
      866,
      880,
      894,
      908,
      922,
      936,
      950,
      964,
      978,
      992,
      1006,
      1006
    ],
    "assigned": [
      24,
      24,
      64,
      92,
      104,
      111,
      111,
      111,
      111,
      111,
      111,
      111,
      111,
      111,
      111,
      111,
      111,
      111,
      111,
      111,
      111,
      111,
      111,
      111,
      111,
      111,
      111,
      111,
      111,
      111
    ],
    "ratio": [
      625,
      654.167,
      381.25,
      567.391,
      540.385,
      627.027,
      639.64,
      652.252,
      664.865,
      677.477,
      690.09,
      702.703,
      715.315,
      727.928,
      740.541,
      750.45,
      760.36,
      770.27,
      780.18,
      792.793,
      805.405,
      818.018,
      830.631,
      843.243,
      855.856,
      868.469,
      881.081,
      893.694,
      906.306,
      906.306
    ],
    "elapsed": [
      0.011,
      0.001,
      1.083,
      0.015,
      0.01,
      0.035,
      0.002,
      0.001,
      0.002,
      0.002,
      0.001,
      0.001,
      0.001,
      0.001,
      0.001,
      0.001,
      0.001,
      0.001,
      0.001,
      0.002,
      0.001,
      0.001,
      0.001,
      0.001,
      0.001,
      0.001,
      0.001,
      0.001,
      0.001,
      0
    ]
  },
  {
    "name": "ClockUp-Heuristic",
    "read": [
      11539,
      11539,
      11579,
      11607,
      11619,
      11626,
      11626,
      11626,
      11626,
      11626,
      11626,
      11626,
      11626,
      11626,
      11626,
      11626,
      11626,
      11626,
      11626,
      11626,
      11627,
      11627,
      11627,
      11627,
      11627,
      11627,
      11627,
      11627,
      11627,
      11627
    ],
    "written": [
      4,
      5,
      924,
      942,
      965,
      1027,
      1028,
      1029,
      1030,
      1034,
      1035,
      1036,
      1037,
      1038,
      1039,
      1042,
      1045,
      1048,
      1051,
      1052,
      1055,
      1056,
      1057,
      1058,
      1059,
      1060,
      1061,
      1062,
      1063,
      1064
    ],
    "pinned": [
      174,
      181,
      308,
      614,
      666,
      807,
      821,
      835,
      849,
      863,
      877,
      891,
      905,
      919,
      933,
      944,
      955,
      966,
      977,
      991,
      1005,
      1019,
      1033,
      1047,
      1061,
      1075,
      1089,
      1103,
      1117,
      1117
    ],
    "unpinned": [
      174,
      181,
      308,
      614,
      666,
      807,
      821,
      835,
      849,
      863,
      877,
      891,
      905,
      919,
      933,
      944,
      955,
      966,
      977,
      991,
      1005,
      1019,
      1033,
      1047,
      1061,
      1075,
      1089,
      1103,
      1117,
      1117
    ],
    "hit": [
      150,
      157,
      244,
      522,
      562,
      696,
      710,
      724,
      738,
      752,
      766,
      780,
      794,
      808,
      822,
      833,
      844,
      855,
      866,
      880,
      894,
      908,
      922,
      936,
      950,
      964,
      978,
      992,
      1006,
      1006
    ],
    "assigned": [
      24,
      24,
      64,
      92,
      104,
      111,
      111,
      111,
      111,
      111,
      111,
      111,
      111,
      111,
      111,
      111,
      111,
      111,
      111,
      111,
      111,
      111,
      111,
      111,
      111,
      111,
      111,
      111,
      111,
      111
    ],
    "ratio": [
      625,
      654.167,
      381.25,
      567.391,
      540.385,
      627.027,
      639.64,
      652.252,
      664.865,
      677.477,
      690.09,
      702.703,
      715.315,
      727.928,
      740.541,
      750.45,
      760.36,
      770.27,
      780.18,
      792.793,
      805.405,
      818.018,
      830.631,
      843.243,
      855.856,
      868.469,
      881.081,
      893.694,
      906.306,
      906.306
    ],
    "elapsed": [
      0.012,
      0.001,
      1.042,
      0.013,
      0.009,
      0.034,
      0.002,
      0.001,
      0.001,
      0.002,
      0.001,
      0.001,
      0.001,
      0.001,
      0.001,
      0.001,
      0.001,
      0.001,
      0.001,
      0.002,
      0.001,
      0.002,
      0.001,
      0.001,
      0.001,
      0.001,
      0.002,
      0.001,
      0.001,
      0
    ]
  }
]
