[
  {
    "name": "Clock-Basic",
    "read": [
      18324,
      18331,
      24616,
      30907,
      30927,
      30945,
      30945
    ],
    "written": [
      4,
      5,
      6,
      7,
      8,
      9,
      13
    ],
    "pinned": [
      287,
      305,
      205955,
      411605,
      422269,
      422919,
      422919
    ],
    "unpinned": [
      287,
      305,
      205955,
      411605,
      422269,
      422919,
      422919
    ],
    "hit": [
      188,
      199,
      199564,
      398923,
      409567,
      410199,
      410199
    ],
    "assigned": [
      99,
      106,
      6391,
      12682,
      12702,
      12720,
      12720
    ],
    "ratio": [
      189.899,
      187.736,
      3122.579,
      3145.584,
      3224.429,
      3224.835,
      3224.835
    ],
    "elapsed": [
      0.018,
      0.002,
      32.688,
      31.541,
      2.18,
      0.06,
      0
    ]
  },
  {
    "name": "Clock-Heuristic",
    "read": [
      18330,
      18338,
      18789,
      19021,
      19049,
      19110,
      19110
    ],
    "written": [
      4,
      5,
      4831,
      4939,
      5015,
      5318,
      5319
    ],
    "pinned": [
      291,
      310,
      849,
      1228,
      1338,
      1537,
      1537
    ],
    "unpinned": [
      291,
      310,
      849,
      1228,
      1338,
      1537,
      1537
    ],
    "hit": [
      186,
      197,
      285,
      432,
      514,
      652,
      652
    ],
    "assigned": [
      105,
      113,
      564,
      796,
      824,
      885,
      885
    ],
    "ratio": [
      177.143,
      174.336,
      50.532,
      54.271,
      62.379,
      73.672,
      73.672
    ],
    "elapsed": [
      0.013,
      0.002,
      2.165,
      0.037,
      0.014,
      0.047,
      0
    ]
  },
  {
    "name": "FIFO-Basic",
    "read": [
      18325,
      18332,
      24742,
      31158,
      31178,
      31196,
      31196
    ],
    "written": [
      4,
      5,
      6,
      7,
      8,
      9,
      13
    ],
    "pinned": [
      287,
      305,
      205955,
      411605,
      422269,
      422919,
      422919
    ],
    "unpinned": [
      287,
      305,
      205955,
      411605,
      422269,
      422919,
      422919
    ],
    "hit": [
      187,
      198,
      199438,
      398672,
      409316,
      409948,
      409948
    ],
    "assigned": [
      100,
      107,
      6517,
      12933,
      12953,
      12971,
      12971
    ],
    "ratio": [
      187,
      185.047,
      3060.273,
      3082.595,
      3160.009,
      3160.497,
      3160.497
    ],
    "elapsed": [
      0.02,
      0.003,
      34.526,
      35.55,
      2.443,
      0.067,
      0
    ]
  },
  {
    "name": "FIFO-Heuristic",
    "read": [
      18331,
      18339,
      18790,
      19021,
      19049,
      19110,
      19110
    ],
    "written": [
      4,
      5,
      4831,
      4942,
      5018,
      5321,
      5322
    ],
    "pinned": [
      291,
      310,
      849,
      1228,
      1338,
      1537,
      1537
    ],
    "unpinned": [
      291,
      310,
      849,
      1228,
      1338,
      1537,
      1537
    ],
    "hit": [
      185,
      196,
      284,
      432,
      514,
      652,
      652
    ],
    "assigned": [
      106,
      114,
      565,
      796,
      824,
      885,
      885
    ],
    "ratio": [
      174.528,
      171.93,
      50.265,
      54.271,
      62.379,
      73.672,
      73.672
    ],
    "elapsed": [
      0.012,
      0.002,
      1.73,
      0.031,
      0.013,
      0.043,
      0
    ]
  },
  {
    "name": "LRU-Basic",
    "read": [
      18319,
      18320,
      23932,
      29548,
      29566,
      29583,
      29583
    ],
    "written": [
      4,
      5,
      6,
      7,
      8,
      9,
      13
    ],
    "pinned": [
      287,
      305,
      205955,
      411605,
      422269,
      422919,
      422919
    ],
    "unpinned": [
      287,
      305,
      205955,
      411605,
      422269,
      422919,
      422919
    ],
    "hit": [
      193,
      210,
      200248,
      400282,
      410928,
      411561,
      411561
    ],
    "assigned": [
      94,
      95,
      5707,
      11323,
      11341,
      11358,
      11358
    ],
    "ratio": [
      205.319,
      221.053,
      3508.814,
      3535.123,
      3623.384,
      3623.534,
      3623.534
    ],
    "elapsed": [
      0.019,
      0.002,
      34.11,
      33.254,
      2.488,
      0.071,
      0
    ]
  },
  {
    "name": "LRU-Heuristic",
    "read": [
      18325,
      18333,
      18784,
      19031,
      19059,
      19120,
      19120
    ],
    "written": [
      4,
      5,
      4831,
      4939,
      5015,
      5318,
      5319
    ],
    "pinned": [
      291,
      310,
      849,
      1228,
      1338,
      1537,
      1537
    ],
    "unpinned": [
      291,
      310,
      849,
      1228,
      1338,
      1537,
      1537
    ],
    "hit": [
      191,
      202,
      290,
      422,
      504,
      642,
      642
    ],
    "assigned": [
      100,
      108,
      559,
      806,
      834,
      895,
      895
    ],
    "ratio": [
      191,
      187.037,
      51.878,
      52.357,
      60.432,
      71.732,
      71.732
    ],
    "elapsed": [
      0.012,
      0.002,
      1.833,
      0.031,
      0.012,
      0.044,
      0
    ]
  },
  {
    "name": "Naive-Basic",
    "read": [
      18400,
      18418,
      224068,
      429716,
      439780,
      439829,
      439829
    ],
    "written": [
      4,
      5,
      6,
      7,
      8,
      9,
      13
    ],
    "pinned": [
      287,
      305,
      205955,
      411605,
      422269,
      422919,
      422919
    ],
    "unpinned": [
      287,
      305,
      205955,
      411605,
      422269,
      422919,
      422919
    ],
    "hit": [
      112,
      112,
      112,
      114,
      714,
      1315,
      1315
    ],
    "assigned": [
      175,
      193,
      205843,
      411491,
      421555,
      421604,
      421604
    ],
    "ratio": [
      64,
      58.031,
      0.054,
      0.028,
      0.169,
      0.312,
      0.312
    ],
    "elapsed": [
      0.018,
      0.002,
      36.472,
      33.684,
      2.338,
      0.06,
      0
    ]
  },
  {
    "name": "Naive-Heuristic",
    "read": [
      18454,
      18473,
      19005,
      19349,
      19444,
      19553,
      19553
    ],
    "written": [
      4,
      5,
      5020,
      5131,
      5209,
      5524,
      5525
    ],
    "pinned": [
      291,
      310,
      849,
      1228,
      1338,
      1537,
      1537
    ],
    "unpinned": [
      291,
      310,
      849,
      1228,
      1338,
      1537,
      1537
    ],
    "hit": [
      62,
      62,
      69,
      104,
      119,
      209,
      209
    ],
    "assigned": [
      229,
      248,
      780,
      1124,
      1219,
      1328,
      1328
    ],
    "ratio": [
      27.074,
      25,
      8.846,
      9.253,
      9.762,
      15.738,
      15.738
    ],
    "elapsed": [
      0.014,
      0.002,
      1.679,
      0.03,
      0.013,
      0.042,
      0
    ]
  },
  {
    "name": "NaiveBis-Basic",
    "read": [
      18400,
      18418,
      224068,
      429716,
      439780,
      439829,
      439829
    ],
    "written": [
      4,
      5,
      6,
      7,
      8,
      9,
      13
    ],
    "pinned": [
      287,
      305,
      205955,
      411605,
      422269,
      422919,
      422919
    ],
    "unpinned": [
      287,
      305,
      205955,
      411605,
      422269,
      422919,
      422919
    ],
    "hit": [
      112,
      112,
      112,
      114,
      714,
      1315,
      1315
    ],
    "assigned": [
      175,
      193,
      205843,
      411491,
      421555,
      421604,
      421604
    ],
    "ratio": [
      64,
      58.031,
      0.054,
      0.028,
      0.169,
      0.312,
      0.312
    ],
    "elapsed": [
      0.017,
      0.002,
      32.772,
      32.893,
      2.235,
      0.054,
      0
    ]
  },
  {
    "name": "NaiveBis-Heuristic",
    "read": [
      18454,
      18473,
      19005,
      19349,
      19444,
      19553,
      19553
    ],
    "written": [
      4,
      5,
      5020,
      5131,
      5209,
      5524,
      5525
    ],
    "pinned": [
      291,
      310,
      849,
      1228,
      1338,
      1537,
      1537
    ],
    "unpinned": [
      291,
      310,
      849,
      1228,
      1338,
      1537,
      1537
    ],
    "hit": [
      62,
      62,
      69,
      104,
      119,
      209,
      209
    ],
    "assigned": [
      229,
      248,
      780,
      1124,
      1219,
      1328,
      1328
    ],
    "ratio": [
      27.074,
      25,
      8.846,
      9.253,
      9.762,
      15.738,
      15.738
    ],
    "elapsed": [
      0.012,
      0.002,
      1.682,
      0.03,
      0.013,
      0.041,
      0
    ]
  }
]
